Workbook

Sheet Input
B1: ACSS Open Data Assesment Tools
B2: Please only fill columns F, N, O, P, Q, R, T and U. The rest of cells will be auto-generated. | E2: Reference Year: | F2: 2021
A3: Code | B3: Section | C3: Category | D3: Indicator | E3: Disaggregation (^ is for ASEAN Only) | F3: Series of data availability Separate years by comma, i.e: 2010, 2017,2018 if 0 number of years are available, leave blank if indicator is not applicable, indicate NA | G3: Count of any years | H3: Count of last 5 Years | I3: Count of last 10 Years | J3: Coverage: Data availability/published for public [C] | N3: Openenness [O] | T3: URL(s) containing respective datasets assessed | U3: Remarks
J4: At least one year [C1] | K4: AT least 3 of the last 5 years [C2] | L4: At least 6 of the last 10 years [C3] | M4: Coverage Sub Score [C1] + [C2] +C3] | N4: Machine Readability [O1] 1 or 0 point | O4: Non Proprietary [O2] 1 or 0 point | P4: Download Options [O3] 1 or 0.5 or 0 point | Q4: Metadata Availability [O4] 1 or 0,5 or 0 point | R4: Term of Use [O5] 1 or 0.5 or 0 point | S4: Openness Sub Score [O1] + [O2] + [03]
A5: SO.POV.POV.001 | B5: Socio-Demography | C5: Poverty | D5: Proportion of Population Living below National Poverty Line (2) | E5: i. Total | G5: =IF(LEN(TRIM(F5)) = 4, 1, IF(LEN(TRIM(F5)) > 5, LEN(TRIM(F5))-LEN(SUBSTITUTE(TRIM(F5),",",""))+1, 0)) -> 0 | H5: =IF(ISNUMBER(SEARCH($F$2, $F5)), 1, 0) + IF(ISNUMBER(SEARCH($F$2-1, $F5)), 1, 0) + IF(ISNUMBER(SEARCH($F$2-2, $F5)), 1, 0) + IF(ISNUMBER(SEARCH($F$2-3, $F5)), 1, 0) + IF(ISNUMBER(SEARCH($F$2-4, $F5)), 1, 0) -> 0 | I5: =IF(ISNUMBER(SEARCH($F$2, $F5)), 1, 0) + IF(ISNUMBER(SEARCH($F$2-1, $F5)), 1, 0) + IF(ISNUMBER(SEARCH($F$2-2, $F5)), 1, 0) + IF(ISNUMBER(SEARCH($F$2-3, $F5)), 1, 0) + IF(ISNUMBER(SEARCH($F$2-4, $F5)), 1, 0) + IF(ISNUMBER(SEARCH($F$2-5, $F5)), 1, 0) + IF(ISNUMBER(SEARCH($F$2-6, $F5)), 1, 0) + IF(ISNUMBER(SEARCH($F$2-7, $F5)), 1, 0) + IF(ISNUMBER(SEARCH($F$2-8, $F5)), 1, 0) + IF(ISNUMBER(SEARCH($F$2-9, $F5)), 1, 0) -> 0 | J5: =IF(F5="NA", "NA", IF(G5>0, 1, 0)) -> 0 | K5: =IF(F5="NA","NA",IF(H5>2,1,IF(H5>1,0.5,0))) -> 0 | L5: =IF(F5="NA","NA",IF(I5>5, 1, IF(I5>2, 0.5, 0))) -> 0 | M5: =SUMIF(J5:L5,"<>#N/A") -> 0 | N5: =IF(F5 = "NA", "NA", 0) -> 0 | O5: =IF(F5 = "NA", "NA", 0) -> 0 | P5: =IF(F5 = "NA", "NA", 0) -> 0 | Q5: =IF(F5 = "NA", "NA", 0) -> 0 | R5: =IF(F5 = "NA", "NA", 0) -> 0 | S5: =SUMIF(N5:R5,"<>#N/A") -> 0
A6: SO.POV.POV.002 | E6: ii. By Sex | G6: =IF(LEN(TRIM(F6)) = 4, 1, IF(LEN(TRIM(F6)) > 5, LEN(TRIM(F6))-LEN(SUBSTITUTE(TRIM(F6),",",""))+1, 0)) -> 0 | H6: =IF(ISNUMBER(SEARCH($F$2, $F6)), 1, 0) + IF(ISNUMBER(SEARCH($F$2-1, $F6)), 1, 0) + IF(ISNUMBER(SEARCH($F$2-2, $F6)), 1, 0) + IF(ISNUMBER(SEARCH($F$2-3, $F6)), 1, 0) + IF(ISNUMBER(SEARCH($F$2-4, $F6)), 1, 0) -> 0 | I6: =IF(ISNUMBER(SEARCH($F$2, $F6)), 1, 0) + IF(ISNUMBER(SEARCH($F$2-1, $F6)), 1, 0) + IF(ISNUMBER(SEARCH($F$2-2, $F6)), 1, 0) + IF(ISNUMBER(SEARCH($F$2-3, $F6)), 1, 0) + IF(ISNUMBER(SEARCH($F$2-4, $F6)), 1, 0) + IF(ISNUMBER(SEARCH($F$2-5, $F6)), 1, 0) + IF(ISNUMBER(SEARCH($F$2-6, $F6)), 1, 0) + IF(ISNUMBER(SEARCH($F$2-7, $F6)), 1, 0) + IF(ISNUMBER(SEARCH($F$2-8, $F6)), 1, 0) + IF(ISNUMBER(SEARCH($F$2-9, $F6)), 1, 0) -> 0 | J6: =IF(F6="NA", "NA", IF(G6>0, 1, 0)) -> 0 | K6: =IF(F6="NA","NA",IF(H6>2,1,IF(H6>1,0.5,0))) -> 0 | L6: =IF(F6="NA","NA",IF(I6>5, 1, IF(I6>2, 0.5, 0))) -> 0 | M6: =SUMIF(J6:L6,"<>#N/A") -> 0 | N6: =IF(F6 = "NA", "NA", 0) -> 0 | O6: =IF(F6 = "NA", "NA", 0) -> 0 | P6: =IF(F6 = "NA", "NA", 0) -> 0 | Q6: =IF(F6 = "NA", "NA", 0) -> 0 | R6: =IF(F6 = "NA", "NA", 0) -> 0 | S6: =SUMIF(N6:R6,"<>#N/A") -> 0
A7: SO.POV.IND.003 | D7: Income Distribution (1) | E7: Decile or Quintile | G7: =IF(LEN(TRIM(F7)) = 4, 1, IF(LEN(TRIM(F7)) > 5, LEN(TRIM(F7))-LEN(SUBSTITUTE(TRIM(F7),",",""))+1, 0)) -> 0 | H7: =IF(ISNUMBER(SEARCH($F$2, $F7)), 1, 0) + IF(ISNUMBER(SEARCH($F$2-1, $F7)), 1, 0) + IF(ISNUMBER(SEARCH($F$2-2, $F7)), 1, 0) + IF(ISNUMBER(SEARCH($F$2-3, $F7)), 1, 0) + IF(ISNUMBER(SEARCH($F$2-4, $F7)), 1, 0) -> 0 | I7: =IF(ISNUMBER(SEARCH($F$2, $F7)), 1, 0) + IF(ISNUMBER(SEARCH($F$2-1, $F7)), 1, 0) + IF(ISNUMBER(SEARCH($F$2-2, $F7)), 1, 0) + IF(ISNUMBER(SEARCH($F$2-3, $F7)), 1, 0) + IF(ISNUMBER(SEARCH($F$2-4, $F7)), 1, 0) + IF(ISNUMBER(SEARCH($F$2-5, $F7)), 1, 0) + IF(ISNUMBER(SEARCH($F$2-6, $F7)), 1, 0) + IF(ISNUMBER(SEARCH($F$2-7, $F7)), 1, 0) + IF(ISNUMBER(SEARCH($F$2-8, $F7)), 1, 0) + IF(ISNUMBER(SEARCH($F$2-9, $F7)), 1, 0) -> 0 | J7: =IF(F7="NA", "NA", IF(G7>0, 1, 0)) -> 0 | K7: =IF(F7="NA","NA",IF(H7>2,1,IF(H7>1,0.5,0))) -> 0 | L7: =IF(F7="NA","NA",IF(I7>5, 1, IF(I7>2, 0.5, 0))) -> 0 | M7: =SUMIF(J7:L7,"<>#N/A") -> 0 | N7: =IF(F7 = "NA", "NA", 0) -> 0 | O7: =IF(F7 = "NA", "NA", 0) -> 0 | P7: =IF(F7 = "NA", "NA", 0) -> 0 | Q7: =IF(F7 = "NA", "NA", 0) -> 0 | R7: =IF(F7 = "NA", "NA", 0) -> 0 | S7: =SUMIF(N7:R7,"<>#N/A") -> 0
A8: SO.POV.GIN.000 | D8: Gini Coefficient (1) | G8: =IF(LEN(TRIM(F8)) = 4, 1, IF(LEN(TRIM(F8)) > 5, LEN(TRIM(F8))-LEN(SUBSTITUTE(TRIM(F8),",",""))+1, 0)) -> 0 | H8: =IF(ISNUMBER(SEARCH($F$2, $F8)), 1, 0) + IF(ISNUMBER(SEARCH($F$2-1, $F8)), 1, 0) + IF(ISNUMBER(SEARCH($F$2-2, $F8)), 1, 0) + IF(ISNUMBER(SEARCH($F$2-3, $F8)), 1, 0) + IF(ISNUMBER(SEARCH($F$2-4, $F8)), 1, 0) -> 0 | I8: =IF(ISNUMBER(SEARCH($F$2, $F8)), 1, 0) + IF(ISNUMBER(SEARCH($F$2-1, $F8)), 1, 0) + IF(ISNUMBER(SEARCH($F$2-2, $F8)), 1, 0) + IF(ISNUMBER(SEARCH($F$2-3, $F8)), 1, 0) + IF(ISNUMBER(SEARCH($F$2-4, $F8)), 1, 0) + IF(ISNUMBER(SEARCH($F$2-5, $F8)), 1, 0) + IF(ISNUMBER(SEARCH($F$2-6, $F8)), 1, 0) + IF(ISNUMBER(SEARCH($F$2-7, $F8)), 1, 0) + IF(ISNUMBER(SEARCH($F$2-8, $F8)), 1, 0) + IF(ISNUMBER(SEARCH($F$2-9, $F8)), 1, 0) -> 0 | J8: =IF(F8="NA", "NA", IF(G8>0, 1, 0)) -> 0 | K8: =IF(F8="NA","NA",IF(H8>2,1,IF(H8>1,0.5,0))) -> 0 | L8: =IF(F8="NA","NA",IF(I8>5, 1, IF(I8>2, 0.5, 0))) -> 0 | M8: =SUMIF(J8:L8,"<>#N/A") -> 0 | N8: =IF(F8 = "NA", "NA", 0) -> 0 | O8: =IF(F8 = "NA", "NA", 0) -> 0 | P8: =IF(F8 = "NA", "NA", 0) -> 0 | Q8: =IF(F8 = "NA", "NA", 0) -> 0 | R8: =IF(F8 = "NA", "NA", 0) -> 0 | S8: =SUMIF(N8:R8,"<>#N/A") -> 0
A9: SO.POP.POP.001 | C9: Population | D9: Population (4) | E9: i. Total | G9: =IF(LEN(TRIM(F9)) = 4, 1, IF(LEN(TRIM(F9)) > 5, LEN(TRIM(F9))-LEN(SUBSTITUTE(TRIM(F9),",",""))+1, 0)) -> 0 | H9: =IF(ISNUMBER(SEARCH($F$2, $F9)), 1, 0) + IF(ISNUMBER(SEARCH($F$2-1, $F9)), 1, 0) + IF(ISNUMBER(SEARCH($F$2-2, $F9)), 1, 0) + IF(ISNUMBER(SEARCH($F$2-3, $F9)), 1, 0) + IF(ISNUMBER(SEARCH($F$2-4, $F9)), 1, 0) -> 0 | I9: =IF(ISNUMBER(SEARCH($F$2, $F9)), 1, 0) + IF(ISNUMBER(SEARCH($F$2-1, $F9)), 1, 0) + IF(ISNUMBER(SEARCH($F$2-2, $F9)), 1, 0) + IF(ISNUMBER(SEARCH($F$2-3, $F9)), 1, 0) + IF(ISNUMBER(SEARCH($F$2-4, $F9)), 1, 0) + IF(ISNUMBER(SEARCH($F$2-5, $F9)), 1, 0) + IF(ISNUMBER(SEARCH($F$2-6, $F9)), 1, 0) + IF(ISNUMBER(SEARCH($F$2-7, $F9)), 1, 0) + IF(ISNUMBER(SEARCH($F$2-8, $F9)), 1, 0) + IF(ISNUMBER(SEARCH($F$2-9, $F9)), 1, 0) -> 0 | J9: =IF(F9="NA", "NA", IF(G9>0, 1, 0)) -> 0 | K9: =IF(F9="NA","NA",IF(H9>2,1,IF(H9>1,0.5,0))) -> 0 | L9: =IF(F9="NA","NA",IF(I9>5, 1, IF(I9>2, 0.5, 0))) -> 0 | M9: =SUMIF(J9:L9,"<>#N/A") -> 0 | N9: 0 | O9: 0 | P9: =IF(F9 = "NA", "NA", 0) -> 0 | Q9: =IF(F9 = "NA", "NA", 0) -> 0 | R9: =IF(F9 = "NA", "NA", 0) -> 0 | S9: =SUMIF(N9:R9,"<>#N/A") -> 0
A10: SO.POP.POP.002 | E10: ii. By Sex | G10: =IF(LEN(TRIM(F10)) = 4, 1, IF(LEN(TRIM(F10)) > 5, LEN(TRIM(F10))-LEN(SUBSTITUTE(TRIM(F10),",",""))+1, 0)) -> 0 | H10: =IF(ISNUMBER(SEARCH($F$2, $F10)), 1, 0) + IF(ISNUMBER(SEARCH($F$2-1, $F10)), 1, 0) + IF(ISNUMBER(SEARCH($F$2-2, $F10)), 1, 0) + IF(ISNUMBER(SEARCH($F$2-3, $F10)), 1, 0) + IF(ISNUMBER(SEARCH($F$2-4, $F10)), 1, 0) -> 0 | I10: =IF(ISNUMBER(SEARCH($F$2, $F10)), 1, 0) + IF(ISNUMBER(SEARCH($F$2-1, $F10)), 1, 0) + IF(ISNUMBER(SEARCH($F$2-2, $F10)), 1, 0) + IF(ISNUMBER(SEARCH($F$2-3, $F10)), 1, 0) + IF(ISNUMBER(SEARCH($F$2-4, $F10)), 1, 0) + IF(ISNUMBER(SEARCH($F$2-5, $F10)), 1, 0) + IF(ISNUMBER(SEARCH($F$2-6, $F10)), 1, 0) + IF(ISNUMBER(SEARCH($F$2-7, $F10)), 1, 0) + IF(ISNUMBER(SEARCH($F$2-8, $F10)), 1, 0) + IF(ISNUMBER(SEARCH($F$2-9, $F10)), 1, 0) -> 0 | J10: =IF(F10="NA", "NA", IF(G10>0, 1, 0)) -> 0 | K10: =IF(F10="NA","NA",IF(H10>2,1,IF(H10>1,0.5,0))) -> 0 | L10: =IF(F10="NA","NA",IF(I10>5, 1, IF(I10>2, 0.5, 0))) -> 0 | M10: =SUMIF(J10:L10,"<>#N/A") -> 0 | N10: =IF(F10 = "NA", "NA", 0) -> 0 | O10: =IF(F10 = "NA", "NA", 0) -> 0 | P10: =IF(F10 = "NA", "NA", 0) -> 0 | Q10: =IF(F10 = "NA", "NA", 0) -> 0 | R10: =IF(F10 = "NA", "NA", 0) -> 0 | S10: =SUMIF(N10:R10,"<>#N/A") -> 0
A11: SO.POP.POP.004 | E11: iii. By Age Group | G11: =IF(LEN(TRIM(F11)) = 4, 1, IF(LEN(TRIM(F11)) > 5, LEN(TRIM(F11))-LEN(SUBSTITUTE(TRIM(F11),",",""))+1, 0)) -> 0 | H11: =IF(ISNUMBER(SEARCH($F$2, $F11)), 1, 0) + IF(ISNUMBER(SEARCH($F$2-1, $F11)), 1, 0) + IF(ISNUMBER(SEARCH($F$2-2, $F11)), 1, 0) + IF(ISNUMBER(SEARCH($F$2-3, $F11)), 1, 0) + IF(ISNUMBER(SEARCH($F$2-4, $F11)), 1, 0) -> 0 | I11: =IF(ISNUMBER(SEARCH($F$2, $F11)), 1, 0) + IF(ISNUMBER(SEARCH($F$2-1, $F11)), 1, 0) + IF(ISNUMBER(SEARCH($F$2-2, $F11)), 1, 0) + IF(ISNUMBER(SEARCH($F$2-3, $F11)), 1, 0) + IF(ISNUMBER(SEARCH($F$2-4, $F11)), 1, 0) + IF(ISNUMBER(SEARCH($F$2-5, $F11)), 1, 0) + IF(ISNUMBER(SEARCH($F$2-6, $F11)), 1, 0) + IF(ISNUMBER(SEARCH($F$2-7, $F11)), 1, 0) + IF(ISNUMBER(SEARCH($F$2-8, $F11)), 1, 0) + IF(ISNUMBER(SEARCH($F$2-9, $F11)), 1, 0) -> 0 | J11: =IF(F11="NA", "NA", IF(G11>0, 1, 0)) -> 0 | K11: =IF(F11="NA","NA",IF(H11>2,1,IF(H11>1,0.5,0))) -> 0 | L11: =IF(F11="NA","NA",IF(I11>5, 1, IF(I11>2, 0.5, 0))) -> 0 | M11: =SUMIF(J11:L11,"<>#N/A") -> 0 | N11: =IF(F11 = "NA", "NA", 0) -> 0 | O11: =IF(F11 = "NA", "NA", 0) -> 0 | P11: =IF(F11 = "NA", "NA", 0) -> 0 | Q11: =IF(F11 = "NA", "NA", 0) -> 0 | R11: =IF(F11 = "NA", "NA", 0) -> 0 | S11: =SUMIF(N11:R11,"<>#N/A") -> 0
A12: SO.POP.POP.005 | E12: iv. By Urban/ Rural/ Slums | G12: =IF(LEN(TRIM(F12)) = 4, 1, IF(LEN(TRIM(F12)) > 5, LEN(TRIM(F12))-LEN(SUBSTITUTE(TRIM(F12),",",""))+1, 0)) -> 0 | H12: =IF(ISNUMBER(SEARCH($F$2, $F12)), 1, 0) + IF(ISNUMBER(SEARCH($F$2-1, $F12)), 1, 0) + IF(ISNUMBER(SEARCH($F$2-2, $F12)), 1, 0) + IF(ISNUMBER(SEARCH($F$2-3, $F12)), 1, 0) + IF(ISNUMBER(SEARCH($F$2-4, $F12)), 1, 0) -> 0 | I12: =IF(ISNUMBER(SEARCH($F$2, $F12)), 1, 0) + IF(ISNUMBER(SEARCH($F$2-1, $F12)), 1, 0) + IF(ISNUMBER(SEARCH($F$2-2, $F12)), 1, 0) + IF(ISNUMBER(SEARCH($F$2-3, $F12)), 1, 0) + IF(ISNUMBER(SEARCH($F$2-4, $F12)), 1, 0) + IF(ISNUMBER(SEARCH($F$2-5, $F12)), 1, 0) + IF(ISNUMBER(SEARCH($F$2-6, $F12)), 1, 0) + IF(ISNUMBER(SEARCH($F$2-7, $F12)), 1, 0) + IF(ISNUMBER(SEARCH($F$2-8, $F12)), 1, 0) + IF(ISNUMBER(SEARCH($F$2-9, $F12)), 1, 0) -> 0 | J12: =IF(F12="NA", "NA", IF(G12>0, 1, 0)) -> 0 | K12: =IF(F12="NA","NA",IF(H12>2,1,IF(H12>1,0.5,0))) -> 0 | L12: =IF(F12="NA","NA",IF(I12>5, 1, IF(I12>2, 0.5, 0))) -> 0 | M12: =SUMIF(J12:L12,"<>#N/A") -> 0 | N12: =IF(F12 = "NA", "NA", 0) -> 0 | O12: =IF(F12 = "NA", "NA", 0) -> 0 | P12: =IF(F12 = "NA", "NA", 0) -> 0 | Q12: =IF(F12 = "NA", "NA", 0) -> 0 | R12: =IF(F12 = "NA", "NA", 0) -> 0 | S12: =SUMIF(N12:R12,"<>#N/A") -> 0
A13: SO.POP.PGR.000 | D13: Population Growth Rate (1) | G13: =IF(LEN(TRIM(F13)) = 4, 1, IF(LEN(TRIM(F13)) > 5, LEN(TRIM(F13))-LEN(SUBSTITUTE(TRIM(F13),",",""))+1, 0)) -> 0 | H13: =IF(ISNUMBER(SEARCH($F$2, $F13)), 1, 0) + IF(ISNUMBER(SEARCH($F$2-1, $F13)), 1, 0) + IF(ISNUMBER(SEARCH($F$2-2, $F13)), 1, 0) + IF(ISNUMBER(SEARCH($F$2-3, $F13)), 1, 0) + IF(ISNUMBER(SEARCH($F$2-4, $F13)), 1, 0) -> 0 | I13: =IF(ISNUMBER(SEARCH($F$2, $F13)), 1, 0) + IF(ISNUMBER(SEARCH($F$2-1, $F13)), 1, 0) + IF(ISNUMBER(SEARCH($F$2-2, $F13)), 1, 0) + IF(ISNUMBER(SEARCH($F$2-3, $F13)), 1, 0) + IF(ISNUMBER(SEARCH($F$2-4, $F13)), 1, 0) + IF(ISNUMBER(SEARCH($F$2-5, $F13)), 1, 0) + IF(ISNUMBER(SEARCH($F$2-6, $F13)), 1, 0) + IF(ISNUMBER(SEARCH($F$2-7, $F13)), 1, 0) + IF(ISNUMBER(SEARCH($F$2-8, $F13)), 1, 0) + IF(ISNUMBER(SEARCH($F$2-9, $F13)), 1, 0) -> 0 | J13: =IF(F13="NA", "NA", IF(G13>0, 1, 0)) -> 0 | K13: =IF(F13="NA","NA",IF(H13>2,1,IF(H13>1,0.5,0))) -> 0 | L13: =IF(F13="NA","NA",IF(I13>5, 1, IF(I13>2, 0.5, 0))) -> 0 | M13: =SUMIF(J13:L13,"<>#N/A") -> 0 | N13: =IF(F13 = "NA", "NA", 0) -> 0 | O13: =IF(F13 = "NA", "NA", 0) -> 0 | P13: =IF(F13 = "NA", "NA", 0) -> 0 | Q13: =IF(F13 = "NA", "NA", 0) -> 0 | R13: =IF(F13 = "NA", "NA", 0) -> 0 | S13: =SUMIF(N13:R13,"<>#N/A") -> 0
A14: SO.POP.PPD.000 | D14: Population Density (1) | G14: =IF(LEN(TRIM(F14)) = 4, 1, IF(LEN(TRIM(F14)) > 5, LEN(TRIM(F14))-LEN(SUBSTITUTE(TRIM(F14),",",""))+1, 0)) -> 0 | H14: =IF(ISNUMBER(SEARCH($F$2, $F14)), 1, 0) + IF(ISNUMBER(SEARCH($F$2-1, $F14)), 1, 0) + IF(ISNUMBER(SEARCH($F$2-2, $F14)), 1, 0) + IF(ISNUMBER(SEARCH($F$2-3, $F14)), 1, 0) + IF(ISNUMBER(SEARCH($F$2-4, $F14)), 1, 0) -> 0 | I14: =IF(ISNUMBER(SEARCH($F$2, $F14)), 1, 0) + IF(ISNUMBER(SEARCH($F$2-1, $F14)), 1, 0) + IF(ISNUMBER(SEARCH($F$2-2, $F14)), 1, 0) + IF(ISNUMBER(SEARCH($F$2-3, $F14)), 1, 0) + IF(ISNUMBER(SEARCH($F$2-4, $F14)), 1, 0) + IF(ISNUMBER(SEARCH($F$2-5, $F14)), 1, 0) + IF(ISNUMBER(SEARCH($F$2-6, $F14)), 1, 0) + IF(ISNUMBER(SEARCH($F$2-7, $F14)), 1, 0) + IF(ISNUMBER(SEARCH($F$2-8, $F14)), 1, 0) + IF(ISNUMBER(SEARCH($F$2-9, $F14)), 1, 0) -> 0 | J14: =IF(F14="NA", "NA", IF(G14>0, 1, 0)) -> 0 | K14: =IF(F14="NA","NA",IF(H14>2,1,IF(H14>1,0.5,0))) -> 0 | L14: =IF(F14="NA","NA",IF(I14>5, 1, IF(I14>2, 0.5, 0))) -> 0 | M14: =SUMIF(J14:L14,"<>#N/A") -> 0 | N14: =IF(F14 = "NA", "NA", 0) -> 0 | O14: =IF(F14 = "NA", "NA", 0) -> 0 | P14: =IF(F14 = "NA", "NA", 0) -> 0 | Q14: =IF(F14 = "NA", "NA", 0) -> 0 | R14: =IF(F14 = "NA", "NA", 0) -> 0 | S14: =SUMIF(N14:R14,"<>#N/A") -> 0
A15: SO.HEW.TFR.000 | C15: Health and Well-Being | D15: Total Fertility Rate (1) | G15: =IF(LEN(TRIM(F15)) = 4, 1, IF(LEN(TRIM(F15)) > 5, LEN(TRIM(F15))-LEN(SUBSTITUTE(TRIM(F15),",",""))+1, 0)) -> 0 | H15: =IF(ISNUMBER(SEARCH($F$2, $F15)), 1, 0) + IF(ISNUMBER(SEARCH($F$2-1, $F15)), 1, 0) + IF(ISNUMBER(SEARCH($F$2-2, $F15)), 1, 0) + IF(ISNUMBER(SEARCH($F$2-3, $F15)), 1, 0) + IF(ISNUMBER(SEARCH($F$2-4, $F15)), 1, 0) -> 0 | I15: =IF(ISNUMBER(SEARCH($F$2, $F15)), 1, 0) + IF(ISNUMBER(SEARCH($F$2-1, $F15)), 1, 0) + IF(ISNUMBER(SEARCH($F$2-2, $F15)), 1, 0) + IF(ISNUMBER(SEARCH($F$2-3, $F15)), 1, 0) + IF(ISNUMBER(SEARCH($F$2-4, $F15)), 1, 0) + IF(ISNUMBER(SEARCH($F$2-5, $F15)), 1, 0) + IF(ISNUMBER(SEARCH($F$2-6, $F15)), 1, 0) + IF(ISNUMBER(SEARCH($F$2-7, $F15)), 1, 0) + IF(ISNUMBER(SEARCH($F$2-8, $F15)), 1, 0) + IF(ISNUMBER(SEARCH($F$2-9, $F15)), 1, 0) -> 0 | J15: =IF(F15="NA", "NA", IF(G15>0, 1, 0)) -> 0 | K15: =IF(F15="NA","NA",IF(H15>2,1,IF(H15>1,0.5,0))) -> 0 | L15: =IF(F15="NA","NA",IF(I15>5, 1, IF(I15>2, 0.5, 0))) -> 0 | M15: =SUMIF(J15:L15,"<>#N/A") -> 0 | N15: =IF(F15 = "NA", "NA", 0) -> 0 | O15: =IF(F15 = "NA", "NA", 0) -> 0 | P15: =IF(F15 = "NA", "NA", 0) -> 0 | Q15: =IF(F15 = "NA", "NA", 0) -> 0 | R15: =IF(F15 = "NA", "NA", 0) -> 0 | S15: =SUMIF(N15:R15,"<>#N/A") -> 0
A16: SO.HEW.LEB.000 | D16: Life Expectancy at Birth (1) | G16: =IF(LEN(TRIM(F16)) = 4, 1, IF(LEN(TRIM(F16)) > 5, LEN(TRIM(F16))-LEN(SUBSTITUTE(TRIM(F16),",",""))+1, 0)) -> 0 | H16: =IF(ISNUMBER(SEARCH($F$2, $F16)), 1, 0) + IF(ISNUMBER(SEARCH($F$2-1, $F16)), 1, 0) + IF(ISNUMBER(SEARCH($F$2-2, $F16)), 1, 0) + IF(ISNUMBER(SEARCH($F$2-3, $F16)), 1, 0) + IF(ISNUMBER(SEARCH($F$2-4, $F16)), 1, 0) -> 0 | I16: =IF(ISNUMBER(SEARCH($F$2, $F16)), 1, 0) + IF(ISNUMBER(SEARCH($F$2-1, $F16)), 1, 0) + IF(ISNUMBER(SEARCH($F$2-2, $F16)), 1, 0) + IF(ISNUMBER(SEARCH($F$2-3, $F16)), 1, 0) + IF(ISNUMBER(SEARCH($F$2-4, $F16)), 1, 0) + IF(ISNUMBER(SEARCH($F$2-5, $F16)), 1, 0) + IF(ISNUMBER(SEARCH($F$2-6, $F16)), 1, 0) + IF(ISNUMBER(SEARCH($F$2-7, $F16)), 1, 0) + IF(ISNUMBER(SEARCH($F$2-8, $F16)), 1, 0) + IF(ISNUMBER(SEARCH($F$2-9, $F16)), 1, 0) -> 0 | J16: =IF(F16="NA", "NA", IF(G16>0, 1, 0)) -> 0 | K16: =IF(F16="NA","NA",IF(H16>2,1,IF(H16>1,0.5,0))) -> 0 | L16: =IF(F16="NA","NA",IF(I16>5, 1, IF(I16>2, 0.5, 0))) -> 0 | M16: =SUMIF(J16:L16,"<>#N/A") -> 0 | N16: =IF(F16 = "NA", "NA", 0) -> 0 | O16: =IF(F16 = "NA", "NA", 0) -> 0 | P16: =IF(F16 = "NA", "NA", 0) -> 0 | Q16: =IF(F16 = "NA", "NA", 0) -> 0 | R16: =IF(F16 = "NA", "NA", 0) -> 0 | S16: =SUMIF(N16:R16,"<>#N/A") -> 0
A17: SO.HEW.MR1.000 | D17: Neonatal Mortality Rate Per 1,000 Live Births (1) | G17: =IF(LEN(TRIM(F17)) = 4, 1, IF(LEN(TRIM(F17)) > 5, LEN(TRIM(F17))-LEN(SUBSTITUTE(TRIM(F17),",",""))+1, 0)) -> 0 | H17: =IF(ISNUMBER(SEARCH($F$2, $F17)), 1, 0) + IF(ISNUMBER(SEARCH($F$2-1, $F17)), 1, 0) + IF(ISNUMBER(SEARCH($F$2-2, $F17)), 1, 0) + IF(ISNUMBER(SEARCH($F$2-3, $F17)), 1, 0) + IF(ISNUMBER(SEARCH($F$2-4, $F17)), 1, 0) -> 0 | I17: =IF(ISNUMBER(SEARCH($F$2, $F17)), 1, 0) + IF(ISNUMBER(SEARCH($F$2-1, $F17)), 1, 0) + IF(ISNUMBER(SEARCH($F$2-2, $F17)), 1, 0) + IF(ISNUMBER(SEARCH($F$2-3, $F17)), 1, 0) + IF(ISNUMBER(SEARCH($F$2-4, $F17)), 1, 0) + IF(ISNUMBER(SEARCH($F$2-5, $F17)), 1, 0) + IF(ISNUMBER(SEARCH($F$2-6, $F17)), 1, 0) + IF(ISNUMBER(SEARCH($F$2-7, $F17)), 1, 0) + IF(ISNUMBER(SEARCH($F$2-8, $F17)), 1, 0) + IF(ISNUMBER(SEARCH($F$2-9, $F17)), 1, 0) -> 0 | J17: =IF(F17="NA", "NA", IF(G17>0, 1, 0)) -> 0 | K17: =IF(F17="NA","NA",IF(H17>2,1,IF(H17>1,0.5,0))) -> 0 | L17: =IF(F17="NA","NA",IF(I17>5, 1, IF(I17>2, 0.5, 0))) -> 0 | M17: =SUMIF(J17:L17,"<>#N/A") -> 0 | N17: =IF(F17 = "NA", "NA", 0) -> 0 | O17: =IF(F17 = "NA", "NA", 0) -> 0 | P17: =IF(F17 = "NA", "NA", 0) -> 0 | Q17: =IF(F17 = "NA", "NA", 0) -> 0 | R17: =IF(F17 = "NA", "NA", 0) -> 0 | S17: =SUMIF(N17:R17,"<>#N/A") -> 0
A18: SO.HEW.MR5.000 | D18: Under-5 Mortality Rate Per 1,000 Live Births (1) | G18: =IF(LEN(TRIM(F18)) = 4, 1, IF(LEN(TRIM(F18)) > 5, LEN(TRIM(F18))-LEN(SUBSTITUTE(TRIM(F18),",",""))+1, 0)) -> 0 | H18: =IF(ISNUMBER(SEARCH($F$2, $F18)), 1, 0) + IF(ISNUMBER(SEARCH($F$2-1, $F18)), 1, 0) + IF(ISNUMBER(SEARCH($F$2-2, $F18)), 1, 0) + IF(ISNUMBER(SEARCH($F$2-3, $F18)), 1, 0) + IF(ISNUMBER(SEARCH($F$2-4, $F18)), 1, 0) -> 0 | I18: =IF(ISNUMBER(SEARCH($F$2, $F18)), 1, 0) + IF(ISNUMBER(SEARCH($F$2-1, $F18)), 1, 0) + IF(ISNUMBER(SEARCH($F$2-2, $F18)), 1, 0) + IF(ISNUMBER(SEARCH($F$2-3, $F18)), 1, 0) + IF(ISNUMBER(SEARCH($F$2-4, $F18)), 1, 0) + IF(ISNUMBER(SEARCH($F$2-5, $F18)), 1, 0) + IF(ISNUMBER(SEARCH($F$2-6, $F18)), 1, 0) + IF(ISNUMBER(SEARCH($F$2-7, $F18)), 1, 0) + IF(ISNUMBER(SEARCH($F$2-8, $F18)), 1, 0) + IF(ISNUMBER(SEARCH($F$2-9, $F18)), 1, 0) -> 0 | J18: =IF(F18="NA", "NA", IF(G18>0, 1, 0)) -> 0 | K18: =IF(F18="NA","NA",IF(H18>2,1,IF(H18>1,0.5,0))) -> 0 | L18: =IF(F18="NA","NA",IF(I18>5, 1, IF(I18>2, 0.5, 0))) -> 0 | M18: =SUMIF(J18:L18,"<>#N/A") -> 0 | N18: =IF(F18 = "NA", "NA", 0) -> 0 | O18: =IF(F18 = "NA", "NA", 0) -> 0 | P18: =IF(F18 = "NA", "NA", 0) -> 0 | Q18: =IF(F18 = "NA", "NA", 0) -> 0 | R18: =IF(F18 = "NA", "NA", 0) -> 0 | S18: =SUMIF(N18:R18,"<>#N/A") -> 0
A19: SO.HEW.MR0.000 | D19: Maternal Mortality Ratio Per 100,000 Live Births (1) | G19: =IF(LEN(TRIM(F19)) = 4, 1, IF(LEN(TRIM(F19)) > 5, LEN(TRIM(F19))-LEN(SUBSTITUTE(TRIM(F19),",",""))+1, 0)) -> 0 | H19: =IF(ISNUMBER(SEARCH($F$2, $F19)), 1, 0) + IF(ISNUMBER(SEARCH($F$2-1, $F19)), 1, 0) + IF(ISNUMBER(SEARCH($F$2-2, $F19)), 1, 0) + IF(ISNUMBER(SEARCH($F$2-3, $F19)), 1, 0) + IF(ISNUMBER(SEARCH($F$2-4, $F19)), 1, 0) -> 0 | I19: =IF(ISNUMBER(SEARCH($F$2, $F19)), 1, 0) + IF(ISNUMBER(SEARCH($F$2-1, $F19)), 1, 0) + IF(ISNUMBER(SEARCH($F$2-2, $F19)), 1, 0) + IF(ISNUMBER(SEARCH($F$2-3, $F19)), 1, 0) + IF(ISNUMBER(SEARCH($F$2-4, $F19)), 1, 0) + IF(ISNUMBER(SEARCH($F$2-5, $F19)), 1, 0) + IF(ISNUMBER(SEARCH($F$2-6, $F19)), 1, 0) + IF(ISNUMBER(SEARCH($F$2-7, $F19)), 1, 0) + IF(ISNUMBER(SEARCH($F$2-8, $F19)), 1, 0) + IF(ISNUMBER(SEARCH($F$2-9, $F19)), 1, 0) -> 0 | J19: =IF(F19="NA", "NA", IF(G19>0, 1, 0)) -> 0 | K19: =IF(F19="NA","NA",IF(H19>2,1,IF(H19>1,0.5,0))) -> 0 | L19: =IF(F19="NA","NA",IF(I19>5, 1, IF(I19>2, 0.5, 0))) -> 0 | M19: =SUMIF(J19:L19,"<>#N/A") -> 0 | N19: =IF(F19 = "NA", "NA", 0) -> 0 | O19: =IF(F19 = "NA", "NA", 0) -> 0 | P19: =IF(F19 = "NA", "NA", 0) -> 0 | Q19: =IF(F19 = "NA", "NA", 0) -> 0 | R19: =IF(F19 = "NA", "NA", 0) -> 0 | S19: =SUMIF(N19:R19,"<>#N/A") -> 0
A20: SO.HEO.STN.000 | C20: Health Outcomes | D20: Prevalence of Stunting and Malnutrition among Children Under 5 Years of Age (1) | G20: =IF(LEN(TRIM(F20)) = 4, 1, IF(LEN(TRIM(F20)) > 5, LEN(TRIM(F20))-LEN(SUBSTITUTE(TRIM(F20),",",""))+1, 0)) -> 0 | H20: =IF(ISNUMBER(SEARCH($F$2, $F20)), 1, 0) + IF(ISNUMBER(SEARCH($F$2-1, $F20)), 1, 0) + IF(ISNUMBER(SEARCH($F$2-2, $F20)), 1, 0) + IF(ISNUMBER(SEARCH($F$2-3, $F20)), 1, 0) + IF(ISNUMBER(SEARCH($F$2-4, $F20)), 1, 0) -> 0 | I20: =IF(ISNUMBER(SEARCH($F$2, $F20)), 1, 0) + IF(ISNUMBER(SEARCH($F$2-1, $F20)), 1, 0) + IF(ISNUMBER(SEARCH($F$2-2, $F20)), 1, 0) + IF(ISNUMBER(SEARCH($F$2-3, $F20)), 1, 0) + IF(ISNUMBER(SEARCH($F$2-4, $F20)), 1, 0) + IF(ISNUMBER(SEARCH($F$2-5, $F20)), 1, 0) + IF(ISNUMBER(SEARCH($F$2-6, $F20)), 1, 0) + IF(ISNUMBER(SEARCH($F$2-7, $F20)), 1, 0) + IF(ISNUMBER(SEARCH($F$2-8, $F20)), 1, 0) + IF(ISNUMBER(SEARCH($F$2-9, $F20)), 1, 0) -> 0 | J20: =IF(F20="NA", "NA", IF(G20>0, 1, 0)) -> 0 | K20: =IF(F20="NA","NA",IF(H20>2,1,IF(H20>1,0.5,0))) -> 0 | L20: =IF(F20="NA","NA",IF(I20>5, 1, IF(I20>2, 0.5, 0))) -> 0 | M20: =SUMIF(J20:L20,"<>#N/A") -> 0 | N20: =IF(F20 = "NA", "NA", 0) -> 0 | O20: =IF(F20 = "NA", "NA", 0) -> 0 | P20: =IF(F20 = "NA", "NA", 0) -> 0 | Q20: =IF(F20 = "NA", "NA", 0) -> 0 | R20: =IF(F20 = "NA", "NA", 0) -> 0 | S20: =SUMIF(N20:R20,"<>#N/A") -> 0
A21: SO.HEO.DIR.006 | D21: Disease Incidence Rate (3) | E21: i. Tuberculosis | G21: =IF(LEN(TRIM(F21)) = 4, 1, IF(LEN(TRIM(F21)) > 5, LEN(TRIM(F21))-LEN(SUBSTITUTE(TRIM(F21),",",""))+1, 0)) -> 0 | H21: =IF(ISNUMBER(SEARCH($F$2, $F21)), 1, 0) + IF(ISNUMBER(SEARCH($F$2-1, $F21)), 1, 0) + IF(ISNUMBER(SEARCH($F$2-2, $F21)), 1, 0) + IF(ISNUMBER(SEARCH($F$2-3, $F21)), 1, 0) + IF(ISNUMBER(SEARCH($F$2-4, $F21)), 1, 0) -> 0 | I21: =IF(ISNUMBER(SEARCH($F$2, $F21)), 1, 0) + IF(ISNUMBER(SEARCH($F$2-1, $F21)), 1, 0) + IF(ISNUMBER(SEARCH($F$2-2, $F21)), 1, 0) + IF(ISNUMBER(SEARCH($F$2-3, $F21)), 1, 0) + IF(ISNUMBER(SEARCH($F$2-4, $F21)), 1, 0) + IF(ISNUMBER(SEARCH($F$2-5, $F21)), 1, 0) + IF(ISNUMBER(SEARCH($F$2-6, $F21)), 1, 0) + IF(ISNUMBER(SEARCH($F$2-7, $F21)), 1, 0) + IF(ISNUMBER(SEARCH($F$2-8, $F21)), 1, 0) + IF(ISNUMBER(SEARCH($F$2-9, $F21)), 1, 0) -> 0 | J21: =IF(F21="NA", "NA", IF(G21>0, 1, 0)) -> 0 | K21: =IF(F21="NA","NA",IF(H21>2,1,IF(H21>1,0.5,0))) -> 0 | L21: =IF(F21="NA","NA",IF(I21>5, 1, IF(I21>2, 0.5, 0))) -> 0 | M21: =SUMIF(J21:L21,"<>#N/A") -> 0 | N21: =IF(F21 = "NA", "NA", 0) -> 0 | O21: =IF(F21 = "NA", "NA", 0) -> 0 | P21: =IF(F21 = "NA", "NA", 0) -> 0 | Q21: =IF(F21 = "NA", "NA", 0) -> 0 | R21: =IF(F21 = "NA", "NA", 0) -> 0 | S21: =SUMIF(N21:R21,"<>#N/A") -> 0
A22: SO.HEO.DIR.007 | E22: ii. Malaria | G22: =IF(LEN(TRIM(F22)) = 4, 1, IF(LEN(TRIM(F22)) > 5, LEN(TRIM(F22))-LEN(SUBSTITUTE(TRIM(F22),",",""))+1, 0)) -> 0 | H22: =IF(ISNUMBER(SEARCH($F$2, $F22)), 1, 0) + IF(ISNUMBER(SEARCH($F$2-1, $F22)), 1, 0) + IF(ISNUMBER(SEARCH($F$2-2, $F22)), 1, 0) + IF(ISNUMBER(SEARCH($F$2-3, $F22)), 1, 0) + IF(ISNUMBER(SEARCH($F$2-4, $F22)), 1, 0) -> 0 | I22: =IF(ISNUMBER(SEARCH($F$2, $F22)), 1, 0) + IF(ISNUMBER(SEARCH($F$2-1, $F22)), 1, 0) + IF(ISNUMBER(SEARCH($F$2-2, $F22)), 1, 0) + IF(ISNUMBER(SEARCH($F$2-3, $F22)), 1, 0) + IF(ISNUMBER(SEARCH($F$2-4, $F22)), 1, 0) + IF(ISNUMBER(SEARCH($F$2-5, $F22)), 1, 0) + IF(ISNUMBER(SEARCH($F$2-6, $F22)), 1, 0) + IF(ISNUMBER(SEARCH($F$2-7, $F22)), 1, 0) + IF(ISNUMBER(SEARCH($F$2-8, $F22)), 1, 0) + IF(ISNUMBER(SEARCH($F$2-9, $F22)), 1, 0) -> 0 | J22: =IF(F22="NA", "NA", IF(G22>0, 1, 0)) -> 0 | K22: =IF(F22="NA","NA",IF(H22>2,1,IF(H22>1,0.5,0))) -> 0 | L22: =IF(F22="NA","NA",IF(I22>5, 1, IF(I22>2, 0.5, 0))) -> 0 | M22: =SUMIF(J22:L22,"<>#N/A") -> 0 | N22: =IF(F22 = "NA", "NA", 0) -> 0 | O22: =IF(F22 = "NA", "NA", 0) -> 0 | P22: =IF(F22 = "NA", "NA", 0) -> 0 | Q22: =IF(F22 = "NA", "NA", 0) -> 0 | R22: =IF(F22 = "NA", "NA", 0) -> 0 | S22: =SUMIF(N22:R22,"<>#N/A") -> 0
A23: SO.HEO.DIR.008 | E23: iii. HIV | G23: =IF(LEN(TRIM(F23)) = 4, 1, IF(LEN(TRIM(F23)) > 5, LEN(TRIM(F23))-LEN(SUBSTITUTE(TRIM(F23),",",""))+1, 0)) -> 0 | H23: =IF(ISNUMBER(SEARCH($F$2, $F23)), 1, 0) + IF(ISNUMBER(SEARCH($F$2-1, $F23)), 1, 0) + IF(ISNUMBER(SEARCH($F$2-2, $F23)), 1, 0) + IF(ISNUMBER(SEARCH($F$2-3, $F23)), 1, 0) + IF(ISNUMBER(SEARCH($F$2-4, $F23)), 1, 0) -> 0 | I23: =IF(ISNUMBER(SEARCH($F$2, $F23)), 1, 0) + IF(ISNUMBER(SEARCH($F$2-1, $F23)), 1, 0) + IF(ISNUMBER(SEARCH($F$2-2, $F23)), 1, 0) + IF(ISNUMBER(SEARCH($F$2-3, $F23)), 1, 0) + IF(ISNUMBER(SEARCH($F$2-4, $F23)), 1, 0) + IF(ISNUMBER(SEARCH($F$2-5, $F23)), 1, 0) + IF(ISNUMBER(SEARCH($F$2-6, $F23)), 1, 0) + IF(ISNUMBER(SEARCH($F$2-7, $F23)), 1, 0) + IF(ISNUMBER(SEARCH($F$2-8, $F23)), 1, 0) + IF(ISNUMBER(SEARCH($F$2-9, $F23)), 1, 0) -> 0 | J23: =IF(F23="NA", "NA", IF(G23>0, 1, 0)) -> 0 | K23: =IF(F23="NA","NA",IF(H23>2,1,IF(H23>1,0.5,0))) -> 0 | L23: =IF(F23="NA","NA",IF(I23>5, 1, IF(I23>2, 0.5, 0))) -> 0 | M23: =SUMIF(J23:L23,"<>#N/A") -> 0 | N23: =IF(F23 = "NA", "NA", 0) -> 0 | O23: =IF(F23 = "NA", "NA", 0) -> 0 | P23: =IF(F23 = "NA", "NA", 0) -> 0 | Q23: =IF(F23 = "NA", "NA", 0) -> 0 | R23: =IF(F23 = "NA", "NA", 0) -> 0 | S23: =SUMIF(N23:R23,"<>#N/A") -> 0
A24: SO.EDU.ENR.001 | C24: Education | D24: Enrolment Ratio (Gross/ Net) (3) | E24: i. Total | G24: =IF(LEN(TRIM(F24)) = 4, 1, IF(LEN(TRIM(F24)) > 5, LEN(TRIM(F24))-LEN(SUBSTITUTE(TRIM(F24),",",""))+1, 0)) -> 0 | H24: =IF(ISNUMBER(SEARCH($F$2, $F24)), 1, 0) + IF(ISNUMBER(SEARCH($F$2-1, $F24)), 1, 0) + IF(ISNUMBER(SEARCH($F$2-2, $F24)), 1, 0) + IF(ISNUMBER(SEARCH($F$2-3, $F24)), 1, 0) + IF(ISNUMBER(SEARCH($F$2-4, $F24)), 1, 0) -> 0 | I24: =IF(ISNUMBER(SEARCH($F$2, $F24)), 1, 0) + IF(ISNUMBER(SEARCH($F$2-1, $F24)), 1, 0) + IF(ISNUMBER(SEARCH($F$2-2, $F24)), 1, 0) + IF(ISNUMBER(SEARCH($F$2-3, $F24)), 1, 0) + IF(ISNUMBER(SEARCH($F$2-4, $F24)), 1, 0) + IF(ISNUMBER(SEARCH($F$2-5, $F24)), 1, 0) + IF(ISNUMBER(SEARCH($F$2-6, $F24)), 1, 0) + IF(ISNUMBER(SEARCH($F$2-7, $F24)), 1, 0) + IF(ISNUMBER(SEARCH($F$2-8, $F24)), 1, 0) + IF(ISNUMBER(SEARCH($F$2-9, $F24)), 1, 0) -> 0 | J24: =IF(F24="NA", "NA", IF(G24>0, 1, 0)) -> 0 | K24: =IF(F24="NA","NA",IF(H24>2,1,IF(H24>1,0.5,0))) -> 0 | L24: =IF(F24="NA","NA",IF(I24>5, 1, IF(I24>2, 0.5, 0))) -> 0 | M24: =SUMIF(J24:L24,"<>#N/A") -> 0 | N24: =IF(F24 = "NA", "NA", 0) -> 0 | O24: =IF(F24 = "NA", "NA", 0) -> 0 | P24: =IF(F24 = "NA", "NA", 0) -> 0 | Q24: =IF(F24 = "NA", "NA", 0) -> 0 | R24: =IF(F24 = "NA", "NA", 0) -> 0 | S24: =SUMIF(N24:R24,"<>#N/A") -> 0
A25: SO.EDU.ENR.002 | E25: ii. By Sex | G25: =IF(LEN(TRIM(F25)) = 4, 1, IF(LEN(TRIM(F25)) > 5, LEN(TRIM(F25))-LEN(SUBSTITUTE(TRIM(F25),",",""))+1, 0)) -> 0 | H25: =IF(ISNUMBER(SEARCH($F$2, $F25)), 1, 0) + IF(ISNUMBER(SEARCH($F$2-1, $F25)), 1, 0) + IF(ISNUMBER(SEARCH($F$2-2, $F25)), 1, 0) + IF(ISNUMBER(SEARCH($F$2-3, $F25)), 1, 0) + IF(ISNUMBER(SEARCH($F$2-4, $F25)), 1, 0) -> 0 | I25: =IF(ISNUMBER(SEARCH($F$2, $F25)), 1, 0) + IF(ISNUMBER(SEARCH($F$2-1, $F25)), 1, 0) + IF(ISNUMBER(SEARCH($F$2-2, $F25)), 1, 0) + IF(ISNUMBER(SEARCH($F$2-3, $F25)), 1, 0) + IF(ISNUMBER(SEARCH($F$2-4, $F25)), 1, 0) + IF(ISNUMBER(SEARCH($F$2-5, $F25)), 1, 0) + IF(ISNUMBER(SEARCH($F$2-6, $F25)), 1, 0) + IF(ISNUMBER(SEARCH($F$2-7, $F25)), 1, 0) + IF(ISNUMBER(SEARCH($F$2-8, $F25)), 1, 0) + IF(ISNUMBER(SEARCH($F$2-9, $F25)), 1, 0) -> 0 | J25: =IF(F25="NA", "NA", IF(G25>0, 1, 0)) -> 0 | K25: =IF(F25="NA","NA",IF(H25>2,1,IF(H25>1,0.5,0))) -> 0 | L25: =IF(F25="NA","NA",IF(I25>5, 1, IF(I25>2, 0.5, 0))) -> 0 | M25: =SUMIF(J25:L25,"<>#N/A") -> 0 | N25: =IF(F25 = "NA", "NA", 0) -> 0 | O25: =IF(F25 = "NA", "NA", 0) -> 0 | P25: =IF(F25 = "NA", "NA", 0) -> 0 | Q25: =IF(F25 = "NA", "NA", 0) -> 0 | R25: =IF(F25 = "NA", "NA", 0) -> 0 | S25: =SUMIF(N25:R25,"<>#N/A") -> 0
A26: SO.EDU.ENR.009 | E26: iii. By Level (Primary, Secondary and Tertiary) | G26: =IF(LEN(TRIM(F26)) = 4, 1, IF(LEN(TRIM(F26)) > 5, LEN(TRIM(F26))-LEN(SUBSTITUTE(TRIM(F26),",",""))+1, 0)) -> 0 | H26: =IF(ISNUMBER(SEARCH($F$2, $F26)), 1, 0) + IF(ISNUMBER(SEARCH($F$2-1, $F26)), 1, 0) + IF(ISNUMBER(SEARCH($F$2-2, $F26)), 1, 0) + IF(ISNUMBER(SEARCH($F$2-3, $F26)), 1, 0) + IF(ISNUMBER(SEARCH($F$2-4, $F26)), 1, 0) -> 0 | I26: =IF(ISNUMBER(SEARCH($F$2, $F26)), 1, 0) + IF(ISNUMBER(SEARCH($F$2-1, $F26)), 1, 0) + IF(ISNUMBER(SEARCH($F$2-2, $F26)), 1, 0) + IF(ISNUMBER(SEARCH($F$2-3, $F26)), 1, 0) + IF(ISNUMBER(SEARCH($F$2-4, $F26)), 1, 0) + IF(ISNUMBER(SEARCH($F$2-5, $F26)), 1, 0) + IF(ISNUMBER(SEARCH($F$2-6, $F26)), 1, 0) + IF(ISNUMBER(SEARCH($F$2-7, $F26)), 1, 0) + IF(ISNUMBER(SEARCH($F$2-8, $F26)), 1, 0) + IF(ISNUMBER(SEARCH($F$2-9, $F26)), 1, 0) -> 0 | J26: =IF(F26="NA", "NA", IF(G26>0, 1, 0)) -> 0 | K26: =IF(F26="NA","NA",IF(H26>2,1,IF(H26>1,0.5,0))) -> 0 | L26: =IF(F26="NA","NA",IF(I26>5, 1, IF(I26>2, 0.5, 0))) -> 0 | M26: =SUMIF(J26:L26,"<>#N/A") -> 0 | N26: =IF(F26 = "NA", "NA", 0) -> 0 | O26: =IF(F26 = "NA", "NA", 0) -> 0 | P26: =IF(F26 = "NA", "NA", 0) -> 0 | Q26: =IF(F26 = "NA", "NA", 0) -> 0 | R26: =IF(F26 = "NA", "NA", 0) -> 0 | S26: =SUMIF(N26:R26,"<>#N/A") -> 0
A27: SO.EDU.ALR.001 | D27: Adult Literacy Rate (2) | E27: i. Total | G27: =IF(LEN(TRIM(F27)) = 4, 1, IF(LEN(TRIM(F27)) > 5, LEN(TRIM(F27))-LEN(SUBSTITUTE(TRIM(F27),",",""))+1, 0)) -> 0 | H27: =IF(ISNUMBER(SEARCH($F$2, $F27)), 1, 0) + IF(ISNUMBER(SEARCH($F$2-1, $F27)), 1, 0) + IF(ISNUMBER(SEARCH($F$2-2, $F27)), 1, 0) + IF(ISNUMBER(SEARCH($F$2-3, $F27)), 1, 0) + IF(ISNUMBER(SEARCH($F$2-4, $F27)), 1, 0) -> 0 | I27: =IF(ISNUMBER(SEARCH($F$2, $F27)), 1, 0) + IF(ISNUMBER(SEARCH($F$2-1, $F27)), 1, 0) + IF(ISNUMBER(SEARCH($F$2-2, $F27)), 1, 0) + IF(ISNUMBER(SEARCH($F$2-3, $F27)), 1, 0) + IF(ISNUMBER(SEARCH($F$2-4, $F27)), 1, 0) + IF(ISNUMBER(SEARCH($F$2-5, $F27)), 1, 0) + IF(ISNUMBER(SEARCH($F$2-6, $F27)), 1, 0) + IF(ISNUMBER(SEARCH($F$2-7, $F27)), 1, 0) + IF(ISNUMBER(SEARCH($F$2-8, $F27)), 1, 0) + IF(ISNUMBER(SEARCH($F$2-9, $F27)), 1, 0) -> 0 | J27: =IF(F27="NA", "NA", IF(G27>0, 1, 0)) -> 0 | K27: =IF(F27="NA","NA",IF(H27>2,1,IF(H27>1,0.5,0))) -> 0 | L27: =IF(F27="NA","NA",IF(I27>5, 1, IF(I27>2, 0.5, 0))) -> 0 | M27: =SUMIF(J27:L27,"<>#N/A") -> 0 | N27: =IF(F27 = "NA", "NA", 0) -> 0 | O27: =IF(F27 = "NA", "NA", 0) -> 0 | P27: =IF(F27 = "NA", "NA", 0) -> 0 | Q27: =IF(F27 = "NA", "NA", 0) -> 0 | R27: =IF(F27 = "NA", "NA", 0) -> 0 | S27: =SUMIF(N27:R27,"<>#N/A") -> 0
A28: SO.EDU.ALR.002 | E28: ii. By Sex | G28: =IF(LEN(TRIM(F28)) = 4, 1, IF(LEN(TRIM(F28)) > 5, LEN(TRIM(F28))-LEN(SUBSTITUTE(TRIM(F28),",",""))+1, 0)) -> 0 | H28: =IF(ISNUMBER(SEARCH($F$2, $F28)), 1, 0) + IF(ISNUMBER(SEARCH($F$2-1, $F28)), 1, 0) + IF(ISNUMBER(SEARCH($F$2-2, $F28)), 1, 0) + IF(ISNUMBER(SEARCH($F$2-3, $F28)), 1, 0) + IF(ISNUMBER(SEARCH($F$2-4, $F28)), 1, 0) -> 0 | I28: =IF(ISNUMBER(SEARCH($F$2, $F28)), 1, 0) + IF(ISNUMBER(SEARCH($F$2-1, $F28)), 1, 0) + IF(ISNUMBER(SEARCH($F$2-2, $F28)), 1, 0) + IF(ISNUMBER(SEARCH($F$2-3, $F28)), 1, 0) + IF(ISNUMBER(SEARCH($F$2-4, $F28)), 1, 0) + IF(ISNUMBER(SEARCH($F$2-5, $F28)), 1, 0) + IF(ISNUMBER(SEARCH($F$2-6, $F28)), 1, 0) + IF(ISNUMBER(SEARCH($F$2-7, $F28)), 1, 0) + IF(ISNUMBER(SEARCH($F$2-8, $F28)), 1, 0) + IF(ISNUMBER(SEARCH($F$2-9, $F28)), 1, 0) -> 0 | J28: =IF(F28="NA", "NA", IF(G28>0, 1, 0)) -> 0 | K28: =IF(F28="NA","NA",IF(H28>2,1,IF(H28>1,0.5,0))) -> 0 | L28: =IF(F28="NA","NA",IF(I28>5, 1, IF(I28>2, 0.5, 0))) -> 0 | M28: =SUMIF(J28:L28,"<>#N/A") -> 0 | N28: =IF(F28 = "NA", "NA", 0) -> 0 | O28: =IF(F28 = "NA", "NA", 0) -> 0 | P28: =IF(F28 = "NA", "NA", 0) -> 0 | Q28: =IF(F28 = "NA", "NA", 0) -> 0 | R28: =IF(F28 = "NA", "NA", 0) -> 0 | S28: =SUMIF(N28:R28,"<>#N/A") -> 0
A29: SO.LAB.UIR.001 | C29: Labour | D29: Unemployment Rate (3) | E29: i. Total | G29: =IF(LEN(TRIM(F29)) = 4, 1, IF(LEN(TRIM(F29)) > 5, LEN(TRIM(F29))-LEN(SUBSTITUTE(TRIM(F29),",",""))+1, 0)) -> 0 | H29: =IF(ISNUMBER(SEARCH($F$2, $F29)), 1, 0) + IF(ISNUMBER(SEARCH($F$2-1, $F29)), 1, 0) + IF(ISNUMBER(SEARCH($F$2-2, $F29)), 1, 0) + IF(ISNUMBER(SEARCH($F$2-3, $F29)), 1, 0) + IF(ISNUMBER(SEARCH($F$2-4, $F29)), 1, 0) -> 0 | I29: =IF(ISNUMBER(SEARCH($F$2, $F29)), 1, 0) + IF(ISNUMBER(SEARCH($F$2-1, $F29)), 1, 0) + IF(ISNUMBER(SEARCH($F$2-2, $F29)), 1, 0) + IF(ISNUMBER(SEARCH($F$2-3, $F29)), 1, 0) + IF(ISNUMBER(SEARCH($F$2-4, $F29)), 1, 0) + IF(ISNUMBER(SEARCH($F$2-5, $F29)), 1, 0) + IF(ISNUMBER(SEARCH($F$2-6, $F29)), 1, 0) + IF(ISNUMBER(SEARCH($F$2-7, $F29)), 1, 0) + IF(ISNUMBER(SEARCH($F$2-8, $F29)), 1, 0) + IF(ISNUMBER(SEARCH($F$2-9, $F29)), 1, 0) -> 0 | J29: =IF(F29="NA", "NA", IF(G29>0, 1, 0)) -> 0 | K29: =IF(F29="NA","NA",IF(H29>2,1,IF(H29>1,0.5,0))) -> 0 | L29: =IF(F29="NA","NA",IF(I29>5, 1, IF(I29>2, 0.5, 0))) -> 0 | M29: =SUMIF(J29:L29,"<>#N/A") -> 0 | N29: =IF(F29 = "NA", "NA", 0) -> 0 | O29: =IF(F29 = "NA", "NA", 0) -> 0 | P29: =IF(F29 = "NA", "NA", 0) -> 0 | Q29: =IF(F29 = "NA", "NA", 0) -> 0 | R29: =IF(F29 = "NA", "NA", 0) -> 0 | S29: =SUMIF(N29:R29,"<>#N/A") -> 0
A30: SO.LAB.UIR.002 | E30: ii. By Sex | G30: =IF(LEN(TRIM(F30)) = 4, 1, IF(LEN(TRIM(F30)) > 5, LEN(TRIM(F30))-LEN(SUBSTITUTE(TRIM(F30),",",""))+1, 0)) -> 0 | H30: =IF(ISNUMBER(SEARCH($F$2, $F30)), 1, 0) + IF(ISNUMBER(SEARCH($F$2-1, $F30)), 1, 0) + IF(ISNUMBER(SEARCH($F$2-2, $F30)), 1, 0) + IF(ISNUMBER(SEARCH($F$2-3, $F30)), 1, 0) + IF(ISNUMBER(SEARCH($F$2-4, $F30)), 1, 0) -> 0 | I30: =IF(ISNUMBER(SEARCH($F$2, $F30)), 1, 0) + IF(ISNUMBER(SEARCH($F$2-1, $F30)), 1, 0) + IF(ISNUMBER(SEARCH($F$2-2, $F30)), 1, 0) + IF(ISNUMBER(SEARCH($F$2-3, $F30)), 1, 0) + IF(ISNUMBER(SEARCH($F$2-4, $F30)), 1, 0) + IF(ISNUMBER(SEARCH($F$2-5, $F30)), 1, 0) + IF(ISNUMBER(SEARCH($F$2-6, $F30)), 1, 0) + IF(ISNUMBER(SEARCH($F$2-7, $F30)), 1, 0) + IF(ISNUMBER(SEARCH($F$2-8, $F30)), 1, 0) + IF(ISNUMBER(SEARCH($F$2-9, $F30)), 1, 0) -> 0 | J30: =IF(F30="NA", "NA", IF(G30>0, 1, 0)) -> 0 | K30: =IF(F30="NA","NA",IF(H30>2,1,IF(H30>1,0.5,0))) -> 0 | L30: =IF(F30="NA","NA",IF(I30>5, 1, IF(I30>2, 0.5, 0))) -> 0 | M30: =SUMIF(J30:L30,"<>#N/A") -> 0 | N30: =IF(F30 = "NA", "NA", 0) -> 0 | O30: =IF(F30 = "NA", "NA", 0) -> 0 | P30: =IF(F30 = "NA", "NA", 0) -> 0 | Q30: =IF(F30 = "NA", "NA", 0) -> 0 | R30: =IF(F30 = "NA", "NA", 0) -> 0 | S30: =SUMIF(N30:R30,"<>#N/A") -> 0
A31: SO.LAB.UIR.010 | E31: iii. By Age | G31: =IF(LEN(TRIM(F31)) = 4, 1, IF(LEN(TRIM(F31)) > 5, LEN(TRIM(F31))-LEN(SUBSTITUTE(TRIM(F31),",",""))+1, 0)) -> 0 | H31: =IF(ISNUMBER(SEARCH($F$2, $F31)), 1, 0) + IF(ISNUMBER(SEARCH($F$2-1, $F31)), 1, 0) + IF(ISNUMBER(SEARCH($F$2-2, $F31)), 1, 0) + IF(ISNUMBER(SEARCH($F$2-3, $F31)), 1, 0) + IF(ISNUMBER(SEARCH($F$2-4, $F31)), 1, 0) -> 0 | I31: =IF(ISNUMBER(SEARCH($F$2, $F31)), 1, 0) + IF(ISNUMBER(SEARCH($F$2-1, $F31)), 1, 0) + IF(ISNUMBER(SEARCH($F$2-2, $F31)), 1, 0) + IF(ISNUMBER(SEARCH($F$2-3, $F31)), 1, 0) + IF(ISNUMBER(SEARCH($F$2-4, $F31)), 1, 0) + IF(ISNUMBER(SEARCH($F$2-5, $F31)), 1, 0) + IF(ISNUMBER(SEARCH($F$2-6, $F31)), 1, 0) + IF(ISNUMBER(SEARCH($F$2-7, $F31)), 1, 0) + IF(ISNUMBER(SEARCH($F$2-8, $F31)), 1, 0) + IF(ISNUMBER(SEARCH($F$2-9, $F31)), 1, 0) -> 0 | J31: =IF(F31="NA", "NA", IF(G31>0, 1, 0)) -> 0 | K31: =IF(F31="NA","NA",IF(H31>2,1,IF(H31>1,0.5,0))) -> 0 | L31: =IF(F31="NA","NA",IF(I31>5, 1, IF(I31>2, 0.5, 0))) -> 0 | M31: =SUMIF(J31:L31,"<>#N/A") -> 0 | N31: =IF(F31 = "NA", "NA", 0) -> 0 | O31: =IF(F31 = "NA", "NA", 0) -> 0 | P31: =IF(F31 = "NA", "NA", 0) -> 0 | Q31: =IF(F31 = "NA", "NA", 0) -> 0 | R31: =IF(F31 = "NA", "NA", 0) -> 0 | S31: =SUMIF(N31:R31,"<>#N/A") -> 0
A32: SO.LAB.PSW.001 | D32: Labour Force Participation Rate (3) | E32: i. Total | G32: =IF(LEN(TRIM(F32)) = 4, 1, IF(LEN(TRIM(F32)) > 5, LEN(TRIM(F32))-LEN(SUBSTITUTE(TRIM(F32),",",""))+1, 0)) -> 0 | H32: =IF(ISNUMBER(SEARCH($F$2, $F32)), 1, 0) + IF(ISNUMBER(SEARCH($F$2-1, $F32)), 1, 0) + IF(ISNUMBER(SEARCH($F$2-2, $F32)), 1, 0) + IF(ISNUMBER(SEARCH($F$2-3, $F32)), 1, 0) + IF(ISNUMBER(SEARCH($F$2-4, $F32)), 1, 0) -> 0 | I32: =IF(ISNUMBER(SEARCH($F$2, $F32)), 1, 0) + IF(ISNUMBER(SEARCH($F$2-1, $F32)), 1, 0) + IF(ISNUMBER(SEARCH($F$2-2, $F32)), 1, 0) + IF(ISNUMBER(SEARCH($F$2-3, $F32)), 1, 0) + IF(ISNUMBER(SEARCH($F$2-4, $F32)), 1, 0) + IF(ISNUMBER(SEARCH($F$2-5, $F32)), 1, 0) + IF(ISNUMBER(SEARCH($F$2-6, $F32)), 1, 0) + IF(ISNUMBER(SEARCH($F$2-7, $F32)), 1, 0) + IF(ISNUMBER(SEARCH($F$2-8, $F32)), 1, 0) + IF(ISNUMBER(SEARCH($F$2-9, $F32)), 1, 0) -> 0 | J32: =IF(F32="NA", "NA", IF(G32>0, 1, 0)) -> 0 | K32: =IF(F32="NA","NA",IF(H32>2,1,IF(H32>1,0.5,0))) -> 0 | L32: =IF(F32="NA","NA",IF(I32>5, 1, IF(I32>2, 0.5, 0))) -> 0 | M32: =SUMIF(J32:L32,"<>#N/A") -> 0 | N32: =IF(F32 = "NA", "NA", 0) -> 0 | O32: =IF(F32 = "NA", "NA", 0) -> 0 | P32: =IF(F32 = "NA", "NA", 0) -> 0 | Q32: =IF(F32 = "NA", "NA", 0) -> 0 | R32: =IF(F32 = "NA", "NA", 0) -> 0 | S32: =SUMIF(N32:R32,"<>#N/A") -> 0
A33: SO.LAB.PSW.002 | E33: ii. By Sex | G33: =IF(LEN(TRIM(F33)) = 4, 1, IF(LEN(TRIM(F33)) > 5, LEN(TRIM(F33))-LEN(SUBSTITUTE(TRIM(F33),",",""))+1, 0)) -> 0 | H33: =IF(ISNUMBER(SEARCH($F$2, $F33)), 1, 0) + IF(ISNUMBER(SEARCH($F$2-1, $F33)), 1, 0) + IF(ISNUMBER(SEARCH($F$2-2, $F33)), 1, 0) + IF(ISNUMBER(SEARCH($F$2-3, $F33)), 1, 0) + IF(ISNUMBER(SEARCH($F$2-4, $F33)), 1, 0) -> 0 | I33: =IF(ISNUMBER(SEARCH($F$2, $F33)), 1, 0) + IF(ISNUMBER(SEARCH($F$2-1, $F33)), 1, 0) + IF(ISNUMBER(SEARCH($F$2-2, $F33)), 1, 0) + IF(ISNUMBER(SEARCH($F$2-3, $F33)), 1, 0) + IF(ISNUMBER(SEARCH($F$2-4, $F33)), 1, 0) + IF(ISNUMBER(SEARCH($F$2-5, $F33)), 1, 0) + IF(ISNUMBER(SEARCH($F$2-6, $F33)), 1, 0) + IF(ISNUMBER(SEARCH($F$2-7, $F33)), 1, 0) + IF(ISNUMBER(SEARCH($F$2-8, $F33)), 1, 0) + IF(ISNUMBER(SEARCH($F$2-9, $F33)), 1, 0) -> 0 | J33: =IF(F33="NA", "NA", IF(G33>0, 1, 0)) -> 0 | K33: =IF(F33="NA","NA",IF(H33>2,1,IF(H33>1,0.5,0))) -> 0 | L33: =IF(F33="NA","NA",IF(I33>5, 1, IF(I33>2, 0.5, 0))) -> 0 | M33: =SUMIF(J33:L33,"<>#N/A") -> 0 | N33: =IF(F33 = "NA", "NA", 0) -> 0 | O33: =IF(F33 = "NA", "NA", 0) -> 0 | P33: =IF(F33 = "NA", "NA", 0) -> 0 | Q33: =IF(F33 = "NA", "NA", 0) -> 0 | R33: =IF(F33 = "NA", "NA", 0) -> 0 | S33: =SUMIF(N33:R33,"<>#N/A") -> 0
A34: SO.LAB.PSW.004 | E34: iii. By Age Group | G34: =IF(LEN(TRIM(F34)) = 4, 1, IF(LEN(TRIM(F34)) > 5, LEN(TRIM(F34))-LEN(SUBSTITUTE(TRIM(F34),",",""))+1, 0)) -> 0 | H34: =IF(ISNUMBER(SEARCH($F$2, $F34)), 1, 0) + IF(ISNUMBER(SEARCH($F$2-1, $F34)), 1, 0) + IF(ISNUMBER(SEARCH($F$2-2, $F34)), 1, 0) + IF(ISNUMBER(SEARCH($F$2-3, $F34)), 1, 0) + IF(ISNUMBER(SEARCH($F$2-4, $F34)), 1, 0) -> 0 | I34: =IF(ISNUMBER(SEARCH($F$2, $F34)), 1, 0) + IF(ISNUMBER(SEARCH($F$2-1, $F34)), 1, 0) + IF(ISNUMBER(SEARCH($F$2-2, $F34)), 1, 0) + IF(ISNUMBER(SEARCH($F$2-3, $F34)), 1, 0) + IF(ISNUMBER(SEARCH($F$2-4, $F34)), 1, 0) + IF(ISNUMBER(SEARCH($F$2-5, $F34)), 1, 0) + IF(ISNUMBER(SEARCH($F$2-6, $F34)), 1, 0) + IF(ISNUMBER(SEARCH($F$2-7, $F34)), 1, 0) + IF(ISNUMBER(SEARCH($F$2-8, $F34)), 1, 0) + IF(ISNUMBER(SEARCH($F$2-9, $F34)), 1, 0) -> 0 | J34: =IF(F34="NA", "NA", IF(G34>0, 1, 0)) -> 0 | K34: =IF(F34="NA","NA",IF(H34>2,1,IF(H34>1,0.5,0))) -> 0 | L34: =IF(F34="NA","NA",IF(I34>5, 1, IF(I34>2, 0.5, 0))) -> 0 | M34: =SUMIF(J34:L34,"<>#N/A") -> 0 | N34: =IF(F34 = "NA", "NA", 0) -> 0 | O34: =IF(F34 = "NA", "NA", 0) -> 0 | P34: =IF(F34 = "NA", "NA", 0) -> 0 | Q34: =IF(F34 = "NA", "NA", 0) -> 0 | R34: =IF(F34 = "NA", "NA", 0) -> 0 | S34: =SUMIF(N34:R34,"<>#N/A") -> 0
A35: SO.GEE.GCP.011 | C35: Gender Equality | D35: Proportion of Seats Held by Women (2) | E35: i. Government/ Parliament | G35: =IF(LEN(TRIM(F35)) = 4, 1, IF(LEN(TRIM(F35)) > 5, LEN(TRIM(F35))-LEN(SUBSTITUTE(TRIM(F35),",",""))+1, 0)) -> 0 | H35: =IF(ISNUMBER(SEARCH($F$2, $F35)), 1, 0) + IF(ISNUMBER(SEARCH($F$2-1, $F35)), 1, 0) + IF(ISNUMBER(SEARCH($F$2-2, $F35)), 1, 0) + IF(ISNUMBER(SEARCH($F$2-3, $F35)), 1, 0) + IF(ISNUMBER(SEARCH($F$2-4, $F35)), 1, 0) -> 0 | I35: =IF(ISNUMBER(SEARCH($F$2, $F35)), 1, 0) + IF(ISNUMBER(SEARCH($F$2-1, $F35)), 1, 0) + IF(ISNUMBER(SEARCH($F$2-2, $F35)), 1, 0) + IF(ISNUMBER(SEARCH($F$2-3, $F35)), 1, 0) + IF(ISNUMBER(SEARCH($F$2-4, $F35)), 1, 0) + IF(ISNUMBER(SEARCH($F$2-5, $F35)), 1, 0) + IF(ISNUMBER(SEARCH($F$2-6, $F35)), 1, 0) + IF(ISNUMBER(SEARCH($F$2-7, $F35)), 1, 0) + IF(ISNUMBER(SEARCH($F$2-8, $F35)), 1, 0) + IF(ISNUMBER(SEARCH($F$2-9, $F35)), 1, 0) -> 0 | J35: =IF(F35="NA", "NA", IF(G35>0, 1, 0)) -> 0 | K35: =IF(F35="NA","NA",IF(H35>2,1,IF(H35>1,0.5,0))) -> 0 | L35: =IF(F35="NA","NA",IF(I35>5, 1, IF(I35>2, 0.5, 0))) -> 0 | M35: =SUMIF(J35:L35,"<>#N/A") -> 0 | N35: =IF(F35 = "NA", "NA", 0) -> 0 | O35: =IF(F35 = "NA", "NA", 0) -> 0 | P35: =IF(F35 = "NA", "NA", 0) -> 0 | Q35: =IF(F35 = "NA", "NA", 0) -> 0 | R35: =IF(F35 = "NA", "NA", 0) -> 0 | S35: =SUMIF(N35:R35,"<>#N/A") -> 0
A36: SO.GEE.GCP.012 | E36: ii. Management Positions | G36: =IF(LEN(TRIM(F36)) = 4, 1, IF(LEN(TRIM(F36)) > 5, LEN(TRIM(F36))-LEN(SUBSTITUTE(TRIM(F36),",",""))+1, 0)) -> 0 | H36: =IF(ISNUMBER(SEARCH($F$2, $F36)), 1, 0) + IF(ISNUMBER(SEARCH($F$2-1, $F36)), 1, 0) + IF(ISNUMBER(SEARCH($F$2-2, $F36)), 1, 0) + IF(ISNUMBER(SEARCH($F$2-3, $F36)), 1, 0) + IF(ISNUMBER(SEARCH($F$2-4, $F36)), 1, 0) -> 0 | I36: =IF(ISNUMBER(SEARCH($F$2, $F36)), 1, 0) + IF(ISNUMBER(SEARCH($F$2-1, $F36)), 1, 0) + IF(ISNUMBER(SEARCH($F$2-2, $F36)), 1, 0) + IF(ISNUMBER(SEARCH($F$2-3, $F36)), 1, 0) + IF(ISNUMBER(SEARCH($F$2-4, $F36)), 1, 0) + IF(ISNUMBER(SEARCH($F$2-5, $F36)), 1, 0) + IF(ISNUMBER(SEARCH($F$2-6, $F36)), 1, 0) + IF(ISNUMBER(SEARCH($F$2-7, $F36)), 1, 0) + IF(ISNUMBER(SEARCH($F$2-8, $F36)), 1, 0) + IF(ISNUMBER(SEARCH($F$2-9, $F36)), 1, 0) -> 0 | J36: =IF(F36="NA", "NA", IF(G36>0, 1, 0)) -> 0 | K36: =IF(F36="NA","NA",IF(H36>2,1,IF(H36>1,0.5,0))) -> 0 | L36: =IF(F36="NA","NA",IF(I36>5, 1, IF(I36>2, 0.5, 0))) -> 0 | M36: =SUMIF(J36:L36,"<>#N/A") -> 0 | N36: =IF(F36 = "NA", "NA", 0) -> 0 | O36: =IF(F36 = "NA", "NA", 0) -> 0 | P36: =IF(F36 = "NA", "NA", 0) -> 0 | Q36: =IF(F36 = "NA", "NA", 0) -> 0 | R36: =IF(F36 = "NA", "NA", 0) -> 0 | S36: =SUMIF(N36:R36,"<>#N/A") -> 0
A37: MA.GDP.FFR.001 | B37: Macroeconomic Indicators | C37: GDP | D37: GDP at Current Prices (2) | E37: i. Total | G37: =IF(LEN(TRIM(F37)) = 4, 1, IF(LEN(TRIM(F37)) > 5, LEN(TRIM(F37))-LEN(SUBSTITUTE(TRIM(F37),",",""))+1, 0)) -> 0 | H37: =IF(ISNUMBER(SEARCH($F$2, $F37)), 1, 0) + IF(ISNUMBER(SEARCH($F$2-1, $F37)), 1, 0) + IF(ISNUMBER(SEARCH($F$2-2, $F37)), 1, 0) + IF(ISNUMBER(SEARCH($F$2-3, $F37)), 1, 0) + IF(ISNUMBER(SEARCH($F$2-4, $F37)), 1, 0) -> 0 | I37: =IF(ISNUMBER(SEARCH($F$2, $F37)), 1, 0) + IF(ISNUMBER(SEARCH($F$2-1, $F37)), 1, 0) + IF(ISNUMBER(SEARCH($F$2-2, $F37)), 1, 0) + IF(ISNUMBER(SEARCH($F$2-3, $F37)), 1, 0) + IF(ISNUMBER(SEARCH($F$2-4, $F37)), 1, 0) + IF(ISNUMBER(SEARCH($F$2-5, $F37)), 1, 0) + IF(ISNUMBER(SEARCH($F$2-6, $F37)), 1, 0) + IF(ISNUMBER(SEARCH($F$2-7, $F37)), 1, 0) + IF(ISNUMBER(SEARCH($F$2-8, $F37)), 1, 0) + IF(ISNUMBER(SEARCH($F$2-9, $F37)), 1, 0) -> 0 | J37: =IF(F37="NA", "NA", IF(G37>0, 1, 0)) -> 0 | K37: =IF(F37="NA","NA",IF(H37>2,1,IF(H37>1,0.5,0))) -> 0 | L37: =IF(F37="NA","NA",IF(I37>5, 1, IF(I37>2, 0.5, 0))) -> 0 | M37: =SUMIF(J37:L37,"<>#N/A") -> 0 | N37: =IF(F37 = "NA", "NA", 0) -> 0 | O37: =IF(F37 = "NA", "NA", 0) -> 0 | P37: =IF(F37 = "NA", "NA", 0) -> 0 | Q37: =IF(F37 = "NA", "NA", 0) -> 0 | R37: =IF(F37 = "NA", "NA", 0) -> 0 | S37: =SUMIF(N37:R37,"<>#N/A") -> 0
A38: MA.GDP.FFR.013 | E38: ii. By Sector/ Industry | G38: =IF(LEN(TRIM(F38)) = 4, 1, IF(LEN(TRIM(F38)) > 5, LEN(TRIM(F38))-LEN(SUBSTITUTE(TRIM(F38),",",""))+1, 0)) -> 0 | H38: =IF(ISNUMBER(SEARCH($F$2, $F38)), 1, 0) + IF(ISNUMBER(SEARCH($F$2-1, $F38)), 1, 0) + IF(ISNUMBER(SEARCH($F$2-2, $F38)), 1, 0) + IF(ISNUMBER(SEARCH($F$2-3, $F38)), 1, 0) + IF(ISNUMBER(SEARCH($F$2-4, $F38)), 1, 0) -> 0 | I38: =IF(ISNUMBER(SEARCH($F$2, $F38)), 1, 0) + IF(ISNUMBER(SEARCH($F$2-1, $F38)), 1, 0) + IF(ISNUMBER(SEARCH($F$2-2, $F38)), 1, 0) + IF(ISNUMBER(SEARCH($F$2-3, $F38)), 1, 0) + IF(ISNUMBER(SEARCH($F$2-4, $F38)), 1, 0) + IF(ISNUMBER(SEARCH($F$2-5, $F38)), 1, 0) + IF(ISNUMBER(SEARCH($F$2-6, $F38)), 1, 0) + IF(ISNUMBER(SEARCH($F$2-7, $F38)), 1, 0) + IF(ISNUMBER(SEARCH($F$2-8, $F38)), 1, 0) + IF(ISNUMBER(SEARCH($F$2-9, $F38)), 1, 0) -> 0 | J38: =IF(F38="NA", "NA", IF(G38>0, 1, 0)) -> 0 | K38: =IF(F38="NA","NA",IF(H38>2,1,IF(H38>1,0.5,0))) -> 0 | L38: =IF(F38="NA","NA",IF(I38>5, 1, IF(I38>2, 0.5, 0))) -> 0 | M38: =SUMIF(J38:L38,"<>#N/A") -> 0 | N38: =IF(F38 = "NA", "NA", 0) -> 0 | O38: =IF(F38 = "NA", "NA", 0) -> 0 | P38: =IF(F38 = "NA", "NA", 0) -> 0 | Q38: =IF(F38 = "NA", "NA", 0) -> 0 | R38: =IF(F38 = "NA", "NA", 0) -> 0 | S38: =SUMIF(N38:R38,"<>#N/A") -> 0
A39: MA.GDP.GPP.000 | D39: GDP Growth Rate at Constant Prices (1) | G39: =IF(LEN(TRIM(F39)) = 4, 1, IF(LEN(TRIM(F39)) > 5, LEN(TRIM(F39))-LEN(SUBSTITUTE(TRIM(F39),",",""))+1, 0)) -> 0 | H39: =IF(ISNUMBER(SEARCH($F$2, $F39)), 1, 0) + IF(ISNUMBER(SEARCH($F$2-1, $F39)), 1, 0) + IF(ISNUMBER(SEARCH($F$2-2, $F39)), 1, 0) + IF(ISNUMBER(SEARCH($F$2-3, $F39)), 1, 0) + IF(ISNUMBER(SEARCH($F$2-4, $F39)), 1, 0) -> 0 | I39: =IF(ISNUMBER(SEARCH($F$2, $F39)), 1, 0) + IF(ISNUMBER(SEARCH($F$2-1, $F39)), 1, 0) + IF(ISNUMBER(SEARCH($F$2-2, $F39)), 1, 0) + IF(ISNUMBER(SEARCH($F$2-3, $F39)), 1, 0) + IF(ISNUMBER(SEARCH($F$2-4, $F39)), 1, 0) + IF(ISNUMBER(SEARCH($F$2-5, $F39)), 1, 0) + IF(ISNUMBER(SEARCH($F$2-6, $F39)), 1, 0) + IF(ISNUMBER(SEARCH($F$2-7, $F39)), 1, 0) + IF(ISNUMBER(SEARCH($F$2-8, $F39)), 1, 0) + IF(ISNUMBER(SEARCH($F$2-9, $F39)), 1, 0) -> 0 | J39: =IF(F39="NA", "NA", IF(G39>0, 1, 0)) -> 0 | K39: =IF(F39="NA","NA",IF(H39>2,1,IF(H39>1,0.5,0))) -> 0 | L39: =IF(F39="NA","NA",IF(I39>5, 1, IF(I39>2, 0.5, 0))) -> 0 | M39: =SUMIF(J39:L39,"<>#N/A") -> 0 | N39: =IF(F39 = "NA", "NA", 0) -> 0 | O39: =IF(F39 = "NA", "NA", 0) -> 0 | P39: =IF(F39 = "NA", "NA", 0) -> 0 | Q39: =IF(F39 = "NA", "NA", 0) -> 0 | R39: =IF(F39 = "NA", "NA", 0) -> 0 | S39: =SUMIF(N39:R39,"<>#N/A") -> 0
A40: MA.GDP.GRR.000 | D40: GDP Per Capita at Current Prices (1) | G40: =IF(LEN(TRIM(F40)) = 4, 1, IF(LEN(TRIM(F40)) > 5, LEN(TRIM(F40))-LEN(SUBSTITUTE(TRIM(F40),",",""))+1, 0)) -> 0 | H40: =IF(ISNUMBER(SEARCH($F$2, $F40)), 1, 0) + IF(ISNUMBER(SEARCH($F$2-1, $F40)), 1, 0) + IF(ISNUMBER(SEARCH($F$2-2, $F40)), 1, 0) + IF(ISNUMBER(SEARCH($F$2-3, $F40)), 1, 0) + IF(ISNUMBER(SEARCH($F$2-4, $F40)), 1, 0) -> 0 | I40: =IF(ISNUMBER(SEARCH($F$2, $F40)), 1, 0) + IF(ISNUMBER(SEARCH($F$2-1, $F40)), 1, 0) + IF(ISNUMBER(SEARCH($F$2-2, $F40)), 1, 0) + IF(ISNUMBER(SEARCH($F$2-3, $F40)), 1, 0) + IF(ISNUMBER(SEARCH($F$2-4, $F40)), 1, 0) + IF(ISNUMBER(SEARCH($F$2-5, $F40)), 1, 0) + IF(ISNUMBER(SEARCH($F$2-6, $F40)), 1, 0) + IF(ISNUMBER(SEARCH($F$2-7, $F40)), 1, 0) + IF(ISNUMBER(SEARCH($F$2-8, $F40)), 1, 0) + IF(ISNUMBER(SEARCH($F$2-9, $F40)), 1, 0) -> 0 | J40: =IF(F40="NA", "NA", IF(G40>0, 1, 0)) -> 0 | K40: =IF(F40="NA","NA",IF(H40>2,1,IF(H40>1,0.5,0))) -> 0 | L40: =IF(F40="NA","NA",IF(I40>5, 1, IF(I40>2, 0.5, 0))) -> 0 | M40: =SUMIF(J40:L40,"<>#N/A") -> 0 | N40: =IF(F40 = "NA", "NA", 0) -> 0 | O40: =IF(F40 = "NA", "NA", 0) -> 0 | P40: =IF(F40 = "NA", "NA", 0) -> 0 | Q40: =IF(F40 = "NA", "NA", 0) -> 0 | R40: =IF(F40 = "NA", "NA", 0) -> 0 | S40: =SUMIF(N40:R40,"<>#N/A") -> 0
A41: MA.GDP.GWR.000 | D41: Growth Rate of Real GDP Per Capita (1) | G41: =IF(LEN(TRIM(F41)) = 4, 1, IF(LEN(TRIM(F41)) > 5, LEN(TRIM(F41))-LEN(SUBSTITUTE(TRIM(F41),",",""))+1, 0)) -> 0 | H41: =IF(ISNUMBER(SEARCH($F$2, $F41)), 1, 0) + IF(ISNUMBER(SEARCH($F$2-1, $F41)), 1, 0) + IF(ISNUMBER(SEARCH($F$2-2, $F41)), 1, 0) + IF(ISNUMBER(SEARCH($F$2-3, $F41)), 1, 0) + IF(ISNUMBER(SEARCH($F$2-4, $F41)), 1, 0) -> 0 | I41: =IF(ISNUMBER(SEARCH($F$2, $F41)), 1, 0) + IF(ISNUMBER(SEARCH($F$2-1, $F41)), 1, 0) + IF(ISNUMBER(SEARCH($F$2-2, $F41)), 1, 0) + IF(ISNUMBER(SEARCH($F$2-3, $F41)), 1, 0) + IF(ISNUMBER(SEARCH($F$2-4, $F41)), 1, 0) + IF(ISNUMBER(SEARCH($F$2-5, $F41)), 1, 0) + IF(ISNUMBER(SEARCH($F$2-6, $F41)), 1, 0) + IF(ISNUMBER(SEARCH($F$2-7, $F41)), 1, 0) + IF(ISNUMBER(SEARCH($F$2-8, $F41)), 1, 0) + IF(ISNUMBER(SEARCH($F$2-9, $F41)), 1, 0) -> 0 | J41: =IF(F41="NA", "NA", IF(G41>0, 1, 0)) -> 0 | K41: =IF(F41="NA","NA",IF(H41>2,1,IF(H41>1,0.5,0))) -> 0 | L41: =IF(F41="NA","NA",IF(I41>5, 1, IF(I41>2, 0.5, 0))) -> 0 | M41: =SUMIF(J41:L41,"<>#N/A") -> 0 | N41: =IF(F41 = "NA", "NA", 0) -> 0 | O41: =IF(F41 = "NA", "NA", 0) -> 0 | P41: =IF(F41 = "NA", "NA", 0) -> 0 | Q41: =IF(F41 = "NA", "NA", 0) -> 0 | R41: =IF(F41 = "NA", "NA", 0) -> 0 | S41: =SUMIF(N41:R41,"<>#N/A") -> 0
A42: MA.MNF.MNF.000 | C42: Manufacturing | D42: Manufacturing (3) | E42: i. Value Added Per Capita | G42: =IF(LEN(TRIM(F42)) = 4, 1, IF(LEN(TRIM(F42)) > 5, LEN(TRIM(F42))-LEN(SUBSTITUTE(TRIM(F42),",",""))+1, 0)) -> 0 | H42: =IF(ISNUMBER(SEARCH($F$2, $F42)), 1, 0) + IF(ISNUMBER(SEARCH($F$2-1, $F42)), 1, 0) + IF(ISNUMBER(SEARCH($F$2-2, $F42)), 1, 0) + IF(ISNUMBER(SEARCH($F$2-3, $F42)), 1, 0) + IF(ISNUMBER(SEARCH($F$2-4, $F42)), 1, 0) -> 0 | I42: =IF(ISNUMBER(SEARCH($F$2, $F42)), 1, 0) + IF(ISNUMBER(SEARCH($F$2-1, $F42)), 1, 0) + IF(ISNUMBER(SEARCH($F$2-2, $F42)), 1, 0) + IF(ISNUMBER(SEARCH($F$2-3, $F42)), 1, 0) + IF(ISNUMBER(SEARCH($F$2-4, $F42)), 1, 0) + IF(ISNUMBER(SEARCH($F$2-5, $F42)), 1, 0) + IF(ISNUMBER(SEARCH($F$2-6, $F42)), 1, 0) + IF(ISNUMBER(SEARCH($F$2-7, $F42)), 1, 0) + IF(ISNUMBER(SEARCH($F$2-8, $F42)), 1, 0) + IF(ISNUMBER(SEARCH($F$2-9, $F42)), 1, 0) -> 0 | J42: =IF(F42="NA", "NA", IF(G42>0, 1, 0)) -> 0 | K42: =IF(F42="NA","NA",IF(H42>2,1,IF(H42>1,0.5,0))) -> 0 | L42: =IF(F42="NA","NA",IF(I42>5, 1, IF(I42>2, 0.5, 0))) -> 0 | M42: =SUMIF(J42:L42,"<>#N/A") -> 0 | N42: =IF(F42 = "NA", "NA", 0) -> 0 | O42: =IF(F42 = "NA", "NA", 0) -> 0 | P42: =IF(F42 = "NA", "NA", 0) -> 0 | Q42: =IF(F42 = "NA", "NA", 0) -> 0 | R42: =IF(F42 = "NA", "NA", 0) -> 0 | S42: =SUMIF(N42:R42,"<>#N/A") -> 0
A43: MA.MNF.MNF.015 | E43: ii. Value Added as a Percentage of GDP | G43: =IF(LEN(TRIM(F43)) = 4, 1, IF(LEN(TRIM(F43)) > 5, LEN(TRIM(F43))-LEN(SUBSTITUTE(TRIM(F43),",",""))+1, 0)) -> 0 | H43: =IF(ISNUMBER(SEARCH($F$2, $F43)), 1, 0) + IF(ISNUMBER(SEARCH($F$2-1, $F43)), 1, 0) + IF(ISNUMBER(SEARCH($F$2-2, $F43)), 1, 0) + IF(ISNUMBER(SEARCH($F$2-3, $F43)), 1, 0) + IF(ISNUMBER(SEARCH($F$2-4, $F43)), 1, 0) -> 0 | I43: =IF(ISNUMBER(SEARCH($F$2, $F43)), 1, 0) + IF(ISNUMBER(SEARCH($F$2-1, $F43)), 1, 0) + IF(ISNUMBER(SEARCH($F$2-2, $F43)), 1, 0) + IF(ISNUMBER(SEARCH($F$2-3, $F43)), 1, 0) + IF(ISNUMBER(SEARCH($F$2-4, $F43)), 1, 0) + IF(ISNUMBER(SEARCH($F$2-5, $F43)), 1, 0) + IF(ISNUMBER(SEARCH($F$2-6, $F43)), 1, 0) + IF(ISNUMBER(SEARCH($F$2-7, $F43)), 1, 0) + IF(ISNUMBER(SEARCH($F$2-8, $F43)), 1, 0) + IF(ISNUMBER(SEARCH($F$2-9, $F43)), 1, 0) -> 0 | J43: =IF(F43="NA", "NA", IF(G43>0, 1, 0)) -> 0 | K43: =IF(F43="NA","NA",IF(H43>2,1,IF(H43>1,0.5,0))) -> 0 | L43: =IF(F43="NA","NA",IF(I43>5, 1, IF(I43>2, 0.5, 0))) -> 0 | M43: =SUMIF(J43:L43,"<>#N/A") -> 0 | N43: =IF(F43 = "NA", "NA", 0) -> 0 | O43: =IF(F43 = "NA", "NA", 0) -> 0 | P43: =IF(F43 = "NA", "NA", 0) -> 0 | Q43: =IF(F43 = "NA", "NA", 0) -> 0 | R43: =IF(F43 = "NA", "NA", 0) -> 0 | S43: =SUMIF(N43:R43,"<>#N/A") -> 0
A44: MA.MNF.MNF.016 | E44: iii. Share to total Employment | G44: =IF(LEN(TRIM(F44)) = 4, 1, IF(LEN(TRIM(F44)) > 5, LEN(TRIM(F44))-LEN(SUBSTITUTE(TRIM(F44),",",""))+1, 0)) -> 0 | H44: =IF(ISNUMBER(SEARCH($F$2, $F44)), 1, 0) + IF(ISNUMBER(SEARCH($F$2-1, $F44)), 1, 0) + IF(ISNUMBER(SEARCH($F$2-2, $F44)), 1, 0) + IF(ISNUMBER(SEARCH($F$2-3, $F44)), 1, 0) + IF(ISNUMBER(SEARCH($F$2-4, $F44)), 1, 0) -> 0 | I44: =IF(ISNUMBER(SEARCH($F$2, $F44)), 1, 0) + IF(ISNUMBER(SEARCH($F$2-1, $F44)), 1, 0) + IF(ISNUMBER(SEARCH($F$2-2, $F44)), 1, 0) + IF(ISNUMBER(SEARCH($F$2-3, $F44)), 1, 0) + IF(ISNUMBER(SEARCH($F$2-4, $F44)), 1, 0) + IF(ISNUMBER(SEARCH($F$2-5, $F44)), 1, 0) + IF(ISNUMBER(SEARCH($F$2-6, $F44)), 1, 0) + IF(ISNUMBER(SEARCH($F$2-7, $F44)), 1, 0) + IF(ISNUMBER(SEARCH($F$2-8, $F44)), 1, 0) + IF(ISNUMBER(SEARCH($F$2-9, $F44)), 1, 0) -> 0 | J44: =IF(F44="NA", "NA", IF(G44>0, 1, 0)) -> 0 | K44: =IF(F44="NA","NA",IF(H44>2,1,IF(H44>1,0.5,0))) -> 0 | L44: =IF(F44="NA","NA",IF(I44>5, 1, IF(I44>2, 0.5, 0))) -> 0 | M44: =SUMIF(J44:L44,"<>#N/A") -> 0 | N44: =IF(F44 = "NA", "NA", 0) -> 0 | O44: =IF(F44 = "NA", "NA", 0) -> 0 | P44: =IF(F44 = "NA", "NA", 0) -> 0 | Q44: =IF(F44 = "NA", "NA", 0) -> 0 | R44: =IF(F44 = "NA", "NA", 0) -> 0 | S44: =SUMIF(N44:R44,"<>#N/A") -> 0
A45: MA.PRC.CPI.001 | C45: Prices | D45: Consumer Price Index (2) | E45: i. Total | G45: =IF(LEN(TRIM(F45)) = 4, 1, IF(LEN(TRIM(F45)) > 5, LEN(TRIM(F45))-LEN(SUBSTITUTE(TRIM(F45),",",""))+1, 0)) -> 0 | H45: =IF(ISNUMBER(SEARCH($F$2, $F45)), 1, 0) + IF(ISNUMBER(SEARCH($F$2-1, $F45)), 1, 0) + IF(ISNUMBER(SEARCH($F$2-2, $F45)), 1, 0) + IF(ISNUMBER(SEARCH($F$2-3, $F45)), 1, 0) + IF(ISNUMBER(SEARCH($F$2-4, $F45)), 1, 0) -> 0 | I45: =IF(ISNUMBER(SEARCH($F$2, $F45)), 1, 0) + IF(ISNUMBER(SEARCH($F$2-1, $F45)), 1, 0) + IF(ISNUMBER(SEARCH($F$2-2, $F45)), 1, 0) + IF(ISNUMBER(SEARCH($F$2-3, $F45)), 1, 0) + IF(ISNUMBER(SEARCH($F$2-4, $F45)), 1, 0) + IF(ISNUMBER(SEARCH($F$2-5, $F45)), 1, 0) + IF(ISNUMBER(SEARCH($F$2-6, $F45)), 1, 0) + IF(ISNUMBER(SEARCH($F$2-7, $F45)), 1, 0) + IF(ISNUMBER(SEARCH($F$2-8, $F45)), 1, 0) + IF(ISNUMBER(SEARCH($F$2-9, $F45)), 1, 0) -> 0 | J45: =IF(F45="NA", "NA", IF(G45>0, 1, 0)) -> 0 | K45: =IF(F45="NA","NA",IF(H45>2,1,IF(H45>1,0.5,0))) -> 0 | L45: =IF(F45="NA","NA",IF(I45>5, 1, IF(I45>2, 0.5, 0))) -> 0 | M45: =SUMIF(J45:L45,"<>#N/A") -> 0 | N45: =IF(F45 = "NA", "NA", 0) -> 0 | O45: =IF(F45 = "NA", "NA", 0) -> 0 | P45: =IF(F45 = "NA", "NA", 0) -> 0 | Q45: =IF(F45 = "NA", "NA", 0) -> 0 | R45: =IF(F45 = "NA", "NA", 0) -> 0 | S45: =SUMIF(N45:R45,"<>#N/A") -> 0
A46: MA.PRC.CPI.017 | E46: ii. By Commodity/ Industry | G46: =IF(LEN(TRIM(F46)) = 4, 1, IF(LEN(TRIM(F46)) > 5, LEN(TRIM(F46))-LEN(SUBSTITUTE(TRIM(F46),",",""))+1, 0)) -> 0 | H46: =IF(ISNUMBER(SEARCH($F$2, $F46)), 1, 0) + IF(ISNUMBER(SEARCH($F$2-1, $F46)), 1, 0) + IF(ISNUMBER(SEARCH($F$2-2, $F46)), 1, 0) + IF(ISNUMBER(SEARCH($F$2-3, $F46)), 1, 0) + IF(ISNUMBER(SEARCH($F$2-4, $F46)), 1, 0) -> 0 | I46: =IF(ISNUMBER(SEARCH($F$2, $F46)), 1, 0) + IF(ISNUMBER(SEARCH($F$2-1, $F46)), 1, 0) + IF(ISNUMBER(SEARCH($F$2-2, $F46)), 1, 0) + IF(ISNUMBER(SEARCH($F$2-3, $F46)), 1, 0) + IF(ISNUMBER(SEARCH($F$2-4, $F46)), 1, 0) + IF(ISNUMBER(SEARCH($F$2-5, $F46)), 1, 0) + IF(ISNUMBER(SEARCH($F$2-6, $F46)), 1, 0) + IF(ISNUMBER(SEARCH($F$2-7, $F46)), 1, 0) + IF(ISNUMBER(SEARCH($F$2-8, $F46)), 1, 0) + IF(ISNUMBER(SEARCH($F$2-9, $F46)), 1, 0) -> 0 | J46: =IF(F46="NA", "NA", IF(G46>0, 1, 0)) -> 0 | K46: =IF(F46="NA","NA",IF(H46>2,1,IF(H46>1,0.5,0))) -> 0 | L46: =IF(F46="NA","NA",IF(I46>5, 1, IF(I46>2, 0.5, 0))) -> 0 | M46: =SUMIF(J46:L46,"<>#N/A") -> 0 | N46: =IF(F46 = "NA", "NA", 0) -> 0 | O46: =IF(F46 = "NA", "NA", 0) -> 0 | P46: =IF(F46 = "NA", "NA", 0) -> 0 | Q46: =IF(F46 = "NA", "NA", 0) -> 0 | R46: =IF(F46 = "NA", "NA", 0) -> 0 | S46: =SUMIF(N46:R46,"<>#N/A") -> 0
A47: MA.PRC.PPI.000 | D47: Producer Price Index (1) | G47: =IF(LEN(TRIM(F47)) = 4, 1, IF(LEN(TRIM(F47)) > 5, LEN(TRIM(F47))-LEN(SUBSTITUTE(TRIM(F47),",",""))+1, 0)) -> 0 | H47: =IF(ISNUMBER(SEARCH($F$2, $F47)), 1, 0) + IF(ISNUMBER(SEARCH($F$2-1, $F47)), 1, 0) + IF(ISNUMBER(SEARCH($F$2-2, $F47)), 1, 0) + IF(ISNUMBER(SEARCH($F$2-3, $F47)), 1, 0) + IF(ISNUMBER(SEARCH($F$2-4, $F47)), 1, 0) -> 0 | I47: =IF(ISNUMBER(SEARCH($F$2, $F47)), 1, 0) + IF(ISNUMBER(SEARCH($F$2-1, $F47)), 1, 0) + IF(ISNUMBER(SEARCH($F$2-2, $F47)), 1, 0) + IF(ISNUMBER(SEARCH($F$2-3, $F47)), 1, 0) + IF(ISNUMBER(SEARCH($F$2-4, $F47)), 1, 0) + IF(ISNUMBER(SEARCH($F$2-5, $F47)), 1, 0) + IF(ISNUMBER(SEARCH($F$2-6, $F47)), 1, 0) + IF(ISNUMBER(SEARCH($F$2-7, $F47)), 1, 0) + IF(ISNUMBER(SEARCH($F$2-8, $F47)), 1, 0) + IF(ISNUMBER(SEARCH($F$2-9, $F47)), 1, 0) -> 0 | J47: =IF(F47="NA", "NA", IF(G47>0, 1, 0)) -> 0 | K47: =IF(F47="NA","NA",IF(H47>2,1,IF(H47>1,0.5,0))) -> 0 | L47: =IF(F47="NA","NA",IF(I47>5, 1, IF(I47>2, 0.5, 0))) -> 0 | M47: =SUMIF(J47:L47,"<>#N/A") -> 0 | N47: =IF(F47 = "NA", "NA", 0) -> 0 | O47: =IF(F47 = "NA", "NA", 0) -> 0 | P47: =IF(F47 = "NA", "NA", 0) -> 0 | Q47: =IF(F47 = "NA", "NA", 0) -> 0 | R47: =IF(F47 = "NA", "NA", 0) -> 0 | S47: =SUMIF(N47:R47,"<>#N/A") -> 0
A48: MA.PRC.IIP.000 | D48: Index of Industrial Production (1) | G48: =IF(LEN(TRIM(F48)) = 4, 1, IF(LEN(TRIM(F48)) > 5, LEN(TRIM(F48))-LEN(SUBSTITUTE(TRIM(F48),",",""))+1, 0)) -> 0 | H48: =IF(ISNUMBER(SEARCH($F$2, $F48)), 1, 0) + IF(ISNUMBER(SEARCH($F$2-1, $F48)), 1, 0) + IF(ISNUMBER(SEARCH($F$2-2, $F48)), 1, 0) + IF(ISNUMBER(SEARCH($F$2-3, $F48)), 1, 0) + IF(ISNUMBER(SEARCH($F$2-4, $F48)), 1, 0) -> 0 | I48: =IF(ISNUMBER(SEARCH($F$2, $F48)), 1, 0) + IF(ISNUMBER(SEARCH($F$2-1, $F48)), 1, 0) + IF(ISNUMBER(SEARCH($F$2-2, $F48)), 1, 0) + IF(ISNUMBER(SEARCH($F$2-3, $F48)), 1, 0) + IF(ISNUMBER(SEARCH($F$2-4, $F48)), 1, 0) + IF(ISNUMBER(SEARCH($F$2-5, $F48)), 1, 0) + IF(ISNUMBER(SEARCH($F$2-6, $F48)), 1, 0) + IF(ISNUMBER(SEARCH($F$2-7, $F48)), 1, 0) + IF(ISNUMBER(SEARCH($F$2-8, $F48)), 1, 0) + IF(ISNUMBER(SEARCH($F$2-9, $F48)), 1, 0) -> 0 | J48: =IF(F48="NA", "NA", IF(G48>0, 1, 0)) -> 0 | K48: =IF(F48="NA","NA",IF(H48>2,1,IF(H48>1,0.5,0))) -> 0 | L48: =IF(F48="NA","NA",IF(I48>5, 1, IF(I48>2, 0.5, 0))) -> 0 | M48: =SUMIF(J48:L48,"<>#N/A") -> 0 | N48: =IF(F48 = "NA", "NA", 0) -> 0 | O48: =IF(F48 = "NA", "NA", 0) -> 0 | P48: =IF(F48 = "NA", "NA", 0) -> 0 | Q48: =IF(F48 = "NA", "NA", 0) -> 0 | R48: =IF(F48 = "NA", "NA", 0) -> 0 | S48: =SUMIF(N48:R48,"<>#N/A") -> 0
A49: MA.PUF.GVF.018 | C49: Public Finance | D49: Government Finance (2) | E49: i. Revenue | G49: =IF(LEN(TRIM(F49)) = 4, 1, IF(LEN(TRIM(F49)) > 5, LEN(TRIM(F49))-LEN(SUBSTITUTE(TRIM(F49),",",""))+1, 0)) -> 0 | H49: =IF(ISNUMBER(SEARCH($F$2, $F49)), 1, 0) + IF(ISNUMBER(SEARCH($F$2-1, $F49)), 1, 0) + IF(ISNUMBER(SEARCH($F$2-2, $F49)), 1, 0) + IF(ISNUMBER(SEARCH($F$2-3, $F49)), 1, 0) + IF(ISNUMBER(SEARCH($F$2-4, $F49)), 1, 0) -> 0 | I49: =IF(ISNUMBER(SEARCH($F$2, $F49)), 1, 0) + IF(ISNUMBER(SEARCH($F$2-1, $F49)), 1, 0) + IF(ISNUMBER(SEARCH($F$2-2, $F49)), 1, 0) + IF(ISNUMBER(SEARCH($F$2-3, $F49)), 1, 0) + IF(ISNUMBER(SEARCH($F$2-4, $F49)), 1, 0) + IF(ISNUMBER(SEARCH($F$2-5, $F49)), 1, 0) + IF(ISNUMBER(SEARCH($F$2-6, $F49)), 1, 0) + IF(ISNUMBER(SEARCH($F$2-7, $F49)), 1, 0) + IF(ISNUMBER(SEARCH($F$2-8, $F49)), 1, 0) + IF(ISNUMBER(SEARCH($F$2-9, $F49)), 1, 0) -> 0 | J49: =IF(F49="NA", "NA", IF(G49>0, 1, 0)) -> 0 | K49: =IF(F49="NA","NA",IF(H49>2,1,IF(H49>1,0.5,0))) -> 0 | L49: =IF(F49="NA","NA",IF(I49>5, 1, IF(I49>2, 0.5, 0))) -> 0 | M49: =SUMIF(J49:L49,"<>#N/A") -> 0 | N49: =IF(F49 = "NA", "NA", 0) -> 0 | O49: =IF(F49 = "NA", "NA", 0) -> 0 | P49: =IF(F49 = "NA", "NA", 0) -> 0 | Q49: =IF(F49 = "NA", "NA", 0) -> 0 | R49: =IF(F49 = "NA", "NA", 0) -> 0 | S49: =SUMIF(N49:R49,"<>#N/A") -> 0
A50: MA.PUF.GVF.019 | E50: ii. Expenditure | G50: =IF(LEN(TRIM(F50)) = 4, 1, IF(LEN(TRIM(F50)) > 5, LEN(TRIM(F50))-LEN(SUBSTITUTE(TRIM(F50),",",""))+1, 0)) -> 0 | H50: =IF(ISNUMBER(SEARCH($F$2, $F50)), 1, 0) + IF(ISNUMBER(SEARCH($F$2-1, $F50)), 1, 0) + IF(ISNUMBER(SEARCH($F$2-2, $F50)), 1, 0) + IF(ISNUMBER(SEARCH($F$2-3, $F50)), 1, 0) + IF(ISNUMBER(SEARCH($F$2-4, $F50)), 1, 0) -> 0 | I50: =IF(ISNUMBER(SEARCH($F$2, $F50)), 1, 0) + IF(ISNUMBER(SEARCH($F$2-1, $F50)), 1, 0) + IF(ISNUMBER(SEARCH($F$2-2, $F50)), 1, 0) + IF(ISNUMBER(SEARCH($F$2-3, $F50)), 1, 0) + IF(ISNUMBER(SEARCH($F$2-4, $F50)), 1, 0) + IF(ISNUMBER(SEARCH($F$2-5, $F50)), 1, 0) + IF(ISNUMBER(SEARCH($F$2-6, $F50)), 1, 0) + IF(ISNUMBER(SEARCH($F$2-7, $F50)), 1, 0) + IF(ISNUMBER(SEARCH($F$2-8, $F50)), 1, 0) + IF(ISNUMBER(SEARCH($F$2-9, $F50)), 1, 0) -> 0 | J50: =IF(F50="NA", "NA", IF(G50>0, 1, 0)) -> 0 | K50: =IF(F50="NA","NA",IF(H50>2,1,IF(H50>1,0.5,0))) -> 0 | L50: =IF(F50="NA","NA",IF(I50>5, 1, IF(I50>2, 0.5, 0))) -> 0 | M50: =SUMIF(J50:L50,"<>#N/A") -> 0 | N50: =IF(F50 = "NA", "NA", 0) -> 0 | O50: =IF(F50 = "NA", "NA", 0) -> 0 | P50: =IF(F50 = "NA", "NA", 0) -> 0 | Q50: =IF(F50 = "NA", "NA", 0) -> 0 | R50: =IF(F50 = "NA", "NA", 0) -> 0 | S50: =SUMIF(N50:R50,"<>#N/A") -> 0
A51: TI.TIG.TIG.020 | B51: Trade and Investment | C51: Trade in Goods | D51: Trade in Goods AMS: (4) ASEANStats: (5) | E51: i. Total by AHTN8 | G51: =IF(LEN(TRIM(F51)) = 4, 1, IF(LEN(TRIM(F51)) > 5, LEN(TRIM(F51))-LEN(SUBSTITUTE(TRIM(F51),",",""))+1, 0)) -> 0 | H51: =IF(ISNUMBER(SEARCH($F$2, $F51)), 1, 0) + IF(ISNUMBER(SEARCH($F$2-1, $F51)), 1, 0) + IF(ISNUMBER(SEARCH($F$2-2, $F51)), 1, 0) + IF(ISNUMBER(SEARCH($F$2-3, $F51)), 1, 0) + IF(ISNUMBER(SEARCH($F$2-4, $F51)), 1, 0) -> 0 | I51: =IF(ISNUMBER(SEARCH($F$2, $F51)), 1, 0) + IF(ISNUMBER(SEARCH($F$2-1, $F51)), 1, 0) + IF(ISNUMBER(SEARCH($F$2-2, $F51)), 1, 0) + IF(ISNUMBER(SEARCH($F$2-3, $F51)), 1, 0) + IF(ISNUMBER(SEARCH($F$2-4, $F51)), 1, 0) + IF(ISNUMBER(SEARCH($F$2-5, $F51)), 1, 0) + IF(ISNUMBER(SEARCH($F$2-6, $F51)), 1, 0) + IF(ISNUMBER(SEARCH($F$2-7, $F51)), 1, 0) + IF(ISNUMBER(SEARCH($F$2-8, $F51)), 1, 0) + IF(ISNUMBER(SEARCH($F$2-9, $F51)), 1, 0) -> 0 | J51: =IF(F51="NA", "NA", IF(G51>0, 1, 0)) -> 0 | K51: =IF(F51="NA","NA",IF(H51>2,1,IF(H51>1,0.5,0))) -> 0 | L51: =IF(F51="NA","NA",IF(I51>5, 1, IF(I51>2, 0.5, 0))) -> 0 | M51: =SUMIF(J51:L51,"<>#N/A") -> 0 | N51: =IF(F51 = "NA", "NA", 0) -> 0 | O51: =IF(F51 = "NA", "NA", 0) -> 0 | P51: =IF(F51 = "NA", "NA", 0) -> 0 | Q51: =IF(F51 = "NA", "NA", 0) -> 0 | R51: =IF(F51 = "NA", "NA", 0) -> 0 | S51: =SUMIF(N51:R51,"<>#N/A") -> 0
A52: TI.TIG.TIG.021 | E52: ii. Export by AHTN8 | G52: =IF(LEN(TRIM(F52)) = 4, 1, IF(LEN(TRIM(F52)) > 5, LEN(TRIM(F52))-LEN(SUBSTITUTE(TRIM(F52),",",""))+1, 0)) -> 0 | H52: =IF(ISNUMBER(SEARCH($F$2, $F52)), 1, 0) + IF(ISNUMBER(SEARCH($F$2-1, $F52)), 1, 0) + IF(ISNUMBER(SEARCH($F$2-2, $F52)), 1, 0) + IF(ISNUMBER(SEARCH($F$2-3, $F52)), 1, 0) + IF(ISNUMBER(SEARCH($F$2-4, $F52)), 1, 0) -> 0 | I52: =IF(ISNUMBER(SEARCH($F$2, $F52)), 1, 0) + IF(ISNUMBER(SEARCH($F$2-1, $F52)), 1, 0) + IF(ISNUMBER(SEARCH($F$2-2, $F52)), 1, 0) + IF(ISNUMBER(SEARCH($F$2-3, $F52)), 1, 0) + IF(ISNUMBER(SEARCH($F$2-4, $F52)), 1, 0) + IF(ISNUMBER(SEARCH($F$2-5, $F52)), 1, 0) + IF(ISNUMBER(SEARCH($F$2-6, $F52)), 1, 0) + IF(ISNUMBER(SEARCH($F$2-7, $F52)), 1, 0) + IF(ISNUMBER(SEARCH($F$2-8, $F52)), 1, 0) + IF(ISNUMBER(SEARCH($F$2-9, $F52)), 1, 0) -> 0 | J52: =IF(F52="NA", "NA", IF(G52>0, 1, 0)) -> 0 | K52: =IF(F52="NA","NA",IF(H52>2,1,IF(H52>1,0.5,0))) -> 0 | L52: =IF(F52="NA","NA",IF(I52>5, 1, IF(I52>2, 0.5, 0))) -> 0 | M52: =SUMIF(J52:L52,"<>#N/A") -> 0 | N52: =IF(F52 = "NA", "NA", 0) -> 0 | O52: =IF(F52 = "NA", "NA", 0) -> 0 | P52: =IF(F52 = "NA", "NA", 0) -> 0 | Q52: =IF(F52 = "NA", "NA", 0) -> 0 | R52: =IF(F52 = "NA", "NA", 0) -> 0 | S52: =SUMIF(N52:R52,"<>#N/A") -> 0
A53: TI.TIG.TIG.022 | E53: iii. Import by AHTN8 | G53: =IF(LEN(TRIM(F53)) = 4, 1, IF(LEN(TRIM(F53)) > 5, LEN(TRIM(F53))-LEN(SUBSTITUTE(TRIM(F53),",",""))+1, 0)) -> 0 | H53: =IF(ISNUMBER(SEARCH($F$2, $F53)), 1, 0) + IF(ISNUMBER(SEARCH($F$2-1, $F53)), 1, 0) + IF(ISNUMBER(SEARCH($F$2-2, $F53)), 1, 0) + IF(ISNUMBER(SEARCH($F$2-3, $F53)), 1, 0) + IF(ISNUMBER(SEARCH($F$2-4, $F53)), 1, 0) -> 0 | I53: =IF(ISNUMBER(SEARCH($F$2, $F53)), 1, 0) + IF(ISNUMBER(SEARCH($F$2-1, $F53)), 1, 0) + IF(ISNUMBER(SEARCH($F$2-2, $F53)), 1, 0) + IF(ISNUMBER(SEARCH($F$2-3, $F53)), 1, 0) + IF(ISNUMBER(SEARCH($F$2-4, $F53)), 1, 0) + IF(ISNUMBER(SEARCH($F$2-5, $F53)), 1, 0) + IF(ISNUMBER(SEARCH($F$2-6, $F53)), 1, 0) + IF(ISNUMBER(SEARCH($F$2-7, $F53)), 1, 0) + IF(ISNUMBER(SEARCH($F$2-8, $F53)), 1, 0) + IF(ISNUMBER(SEARCH($F$2-9, $F53)), 1, 0) -> 0 | J53: =IF(F53="NA", "NA", IF(G53>0, 1, 0)) -> 0 | K53: =IF(F53="NA","NA",IF(H53>2,1,IF(H53>1,0.5,0))) -> 0 | L53: =IF(F53="NA","NA",IF(I53>5, 1, IF(I53>2, 0.5, 0))) -> 0 | M53: =SUMIF(J53:L53,"<>#N/A") -> 0 | N53: =IF(F53 = "NA", "NA", 0) -> 0 | O53: =IF(F53 = "NA", "NA", 0) -> 0 | P53: =IF(F53 = "NA", "NA", 0) -> 0 | Q53: =IF(F53 = "NA", "NA", 0) -> 0 | R53: =IF(F53 = "NA", "NA", 0) -> 0 | S53: =SUMIF(N53:R53,"<>#N/A") -> 0
A54: TI.TIG.TIG.023 | E54: iv. By Country/ Region | G54: =IF(LEN(TRIM(F54)) = 4, 1, IF(LEN(TRIM(F54)) > 5, LEN(TRIM(F54))-LEN(SUBSTITUTE(TRIM(F54),",",""))+1, 0)) -> 0 | H54: =IF(ISNUMBER(SEARCH($F$2, $F54)), 1, 0) + IF(ISNUMBER(SEARCH($F$2-1, $F54)), 1, 0) + IF(ISNUMBER(SEARCH($F$2-2, $F54)), 1, 0) + IF(ISNUMBER(SEARCH($F$2-3, $F54)), 1, 0) + IF(ISNUMBER(SEARCH($F$2-4, $F54)), 1, 0) -> 0 | I54: =IF(ISNUMBER(SEARCH($F$2, $F54)), 1, 0) + IF(ISNUMBER(SEARCH($F$2-1, $F54)), 1, 0) + IF(ISNUMBER(SEARCH($F$2-2, $F54)), 1, 0) + IF(ISNUMBER(SEARCH($F$2-3, $F54)), 1, 0) + IF(ISNUMBER(SEARCH($F$2-4, $F54)), 1, 0) + IF(ISNUMBER(SEARCH($F$2-5, $F54)), 1, 0) + IF(ISNUMBER(SEARCH($F$2-6, $F54)), 1, 0) + IF(ISNUMBER(SEARCH($F$2-7, $F54)), 1, 0) + IF(ISNUMBER(SEARCH($F$2-8, $F54)), 1, 0) + IF(ISNUMBER(SEARCH($F$2-9, $F54)), 1, 0) -> 0 | J54: =IF(F54="NA", "NA", IF(G54>0, 1, 0)) -> 0 | K54: =IF(F54="NA","NA",IF(H54>2,1,IF(H54>1,0.5,0))) -> 0 | L54: =IF(F54="NA","NA",IF(I54>5, 1, IF(I54>2, 0.5, 0))) -> 0 | M54: =SUMIF(J54:L54,"<>#N/A") -> 0 | N54: =IF(F54 = "NA", "NA", 0) -> 0 | O54: =IF(F54 = "NA", "NA", 0) -> 0 | P54: =IF(F54 = "NA", "NA", 0) -> 0 | Q54: =IF(F54 = "NA", "NA", 0) -> 0 | R54: =IF(F54 = "NA", "NA", 0) -> 0 | S54: =SUMIF(N54:R54,"<>#N/A") -> 0
A55: TI.TIG.TIG.024 | E55: v. By Intra, Extra ^ | F55: NA | G55: =IF(LEN(TRIM(F55)) = 4, 1, IF(LEN(TRIM(F55)) > 5, LEN(TRIM(F55))-LEN(SUBSTITUTE(TRIM(F55),",",""))+1, 0)) -> 0 | H55: =IF(ISNUMBER(SEARCH($F$2, $F55)), 1, 0) + IF(ISNUMBER(SEARCH($F$2-1, $F55)), 1, 0) + IF(ISNUMBER(SEARCH($F$2-2, $F55)), 1, 0) + IF(ISNUMBER(SEARCH($F$2-3, $F55)), 1, 0) + IF(ISNUMBER(SEARCH($F$2-4, $F55)), 1, 0) -> 0 | I55: =IF(ISNUMBER(SEARCH($F$2, $F55)), 1, 0) + IF(ISNUMBER(SEARCH($F$2-1, $F55)), 1, 0) + IF(ISNUMBER(SEARCH($F$2-2, $F55)), 1, 0) + IF(ISNUMBER(SEARCH($F$2-3, $F55)), 1, 0) + IF(ISNUMBER(SEARCH($F$2-4, $F55)), 1, 0) + IF(ISNUMBER(SEARCH($F$2-5, $F55)), 1, 0) + IF(ISNUMBER(SEARCH($F$2-6, $F55)), 1, 0) + IF(ISNUMBER(SEARCH($F$2-7, $F55)), 1, 0) + IF(ISNUMBER(SEARCH($F$2-8, $F55)), 1, 0) + IF(ISNUMBER(SEARCH($F$2-9, $F55)), 1, 0) -> 0 | J55: =IF(F55="NA", "NA", IF(G55>0, 1, 0)) -> NA | K55: =IF(F55="NA","NA",IF(H55>2,1,IF(H55>1,0.5,0))) -> NA | L55: =IF(F55="NA","NA",IF(I55>5, 1, IF(I55>2, 0.5, 0))) -> NA | M55: =SUMIF(J55:L55,"<>#N/A") -> 0 | N55: =IF(F55 = "NA", "NA", 0) -> NA | O55: =IF(F55 = "NA", "NA", 0) -> NA | P55: =IF(F55 = "NA", "NA", 0) -> NA | Q55: =IF(F55 = "NA", "NA", 0) -> NA | R55: =IF(F55 = "NA", "NA", 0) -> NA | S55: =SUMIF(N55:R55,"<>#N/A") -> 0 | T55: NA | U55: NA
A56: TI.TIS.TIS.001 | C56: Trade in Services | D56: Trade in Services AMS: (5) ASEANStats: (6) | E56: i. Total | G56: =IF(LEN(TRIM(F56)) = 4, 1, IF(LEN(TRIM(F56)) > 5, LEN(TRIM(F56))-LEN(SUBSTITUTE(TRIM(F56),",",""))+1, 0)) -> 0 | H56: =IF(ISNUMBER(SEARCH($F$2, $F56)), 1, 0) + IF(ISNUMBER(SEARCH($F$2-1, $F56)), 1, 0) + IF(ISNUMBER(SEARCH($F$2-2, $F56)), 1, 0) + IF(ISNUMBER(SEARCH($F$2-3, $F56)), 1, 0) + IF(ISNUMBER(SEARCH($F$2-4, $F56)), 1, 0) -> 0 | I56: =IF(ISNUMBER(SEARCH($F$2, $F56)), 1, 0) + IF(ISNUMBER(SEARCH($F$2-1, $F56)), 1, 0) + IF(ISNUMBER(SEARCH($F$2-2, $F56)), 1, 0) + IF(ISNUMBER(SEARCH($F$2-3, $F56)), 1, 0) + IF(ISNUMBER(SEARCH($F$2-4, $F56)), 1, 0) + IF(ISNUMBER(SEARCH($F$2-5, $F56)), 1, 0) + IF(ISNUMBER(SEARCH($F$2-6, $F56)), 1, 0) + IF(ISNUMBER(SEARCH($F$2-7, $F56)), 1, 0) + IF(ISNUMBER(SEARCH($F$2-8, $F56)), 1, 0) + IF(ISNUMBER(SEARCH($F$2-9, $F56)), 1, 0) -> 0 | J56: =IF(F56="NA", "NA", IF(G56>0, 1, 0)) -> 0 | K56: =IF(F56="NA","NA",IF(H56>2,1,IF(H56>1,0.5,0))) -> 0 | L56: =IF(F56="NA","NA",IF(I56>5, 1, IF(I56>2, 0.5, 0))) -> 0 | M56: =SUMIF(J56:L56,"<>#N/A") -> 0 | N56: =IF(F56 = "NA", "NA", 0) -> 0 | O56: =IF(F56 = "NA", "NA", 0) -> 0 | P56: =IF(F56 = "NA", "NA", 0) -> 0 | Q56: =IF(F56 = "NA", "NA", 0) -> 0 | R56: =IF(F56 = "NA", "NA", 0) -> 0 | S56: =SUMIF(N56:R56,"<>#N/A") -> 0
A57: TI.TIS.TIS.025 | E57: ii. Export | G57: =IF(LEN(TRIM(F57)) = 4, 1, IF(LEN(TRIM(F57)) > 5, LEN(TRIM(F57))-LEN(SUBSTITUTE(TRIM(F57),",",""))+1, 0)) -> 0 | H57: =IF(ISNUMBER(SEARCH($F$2, $F57)), 1, 0) + IF(ISNUMBER(SEARCH($F$2-1, $F57)), 1, 0) + IF(ISNUMBER(SEARCH($F$2-2, $F57)), 1, 0) + IF(ISNUMBER(SEARCH($F$2-3, $F57)), 1, 0) + IF(ISNUMBER(SEARCH($F$2-4, $F57)), 1, 0) -> 0 | I57: =IF(ISNUMBER(SEARCH($F$2, $F57)), 1, 0) + IF(ISNUMBER(SEARCH($F$2-1, $F57)), 1, 0) + IF(ISNUMBER(SEARCH($F$2-2, $F57)), 1, 0) + IF(ISNUMBER(SEARCH($F$2-3, $F57)), 1, 0) + IF(ISNUMBER(SEARCH($F$2-4, $F57)), 1, 0) + IF(ISNUMBER(SEARCH($F$2-5, $F57)), 1, 0) + IF(ISNUMBER(SEARCH($F$2-6, $F57)), 1, 0) + IF(ISNUMBER(SEARCH($F$2-7, $F57)), 1, 0) + IF(ISNUMBER(SEARCH($F$2-8, $F57)), 1, 0) + IF(ISNUMBER(SEARCH($F$2-9, $F57)), 1, 0) -> 0 | J57: =IF(F57="NA", "NA", IF(G57>0, 1, 0)) -> 0 | K57: =IF(F57="NA","NA",IF(H57>2,1,IF(H57>1,0.5,0))) -> 0 | L57: =IF(F57="NA","NA",IF(I57>5, 1, IF(I57>2, 0.5, 0))) -> 0 | M57: =SUMIF(J57:L57,"<>#N/A") -> 0 | N57: =IF(F57 = "NA", "NA", 0) -> 0 | O57: =IF(F57 = "NA", "NA", 0) -> 0 | P57: =IF(F57 = "NA", "NA", 0) -> 0 | Q57: =IF(F57 = "NA", "NA", 0) -> 0 | R57: =IF(F57 = "NA", "NA", 0) -> 0 | S57: =SUMIF(N57:R57,"<>#N/A") -> 0
A58: TI.TIS.TIS.026 | E58: iii. Import | G58: =IF(LEN(TRIM(F58)) = 4, 1, IF(LEN(TRIM(F58)) > 5, LEN(TRIM(F58))-LEN(SUBSTITUTE(TRIM(F58),",",""))+1, 0)) -> 0 | H58: =IF(ISNUMBER(SEARCH($F$2, $F58)), 1, 0) + IF(ISNUMBER(SEARCH($F$2-1, $F58)), 1, 0) + IF(ISNUMBER(SEARCH($F$2-2, $F58)), 1, 0) + IF(ISNUMBER(SEARCH($F$2-3, $F58)), 1, 0) + IF(ISNUMBER(SEARCH($F$2-4, $F58)), 1, 0) -> 0 | I58: =IF(ISNUMBER(SEARCH($F$2, $F58)), 1, 0) + IF(ISNUMBER(SEARCH($F$2-1, $F58)), 1, 0) + IF(ISNUMBER(SEARCH($F$2-2, $F58)), 1, 0) + IF(ISNUMBER(SEARCH($F$2-3, $F58)), 1, 0) + IF(ISNUMBER(SEARCH($F$2-4, $F58)), 1, 0) + IF(ISNUMBER(SEARCH($F$2-5, $F58)), 1, 0) + IF(ISNUMBER(SEARCH($F$2-6, $F58)), 1, 0) + IF(ISNUMBER(SEARCH($F$2-7, $F58)), 1, 0) + IF(ISNUMBER(SEARCH($F$2-8, $F58)), 1, 0) + IF(ISNUMBER(SEARCH($F$2-9, $F58)), 1, 0) -> 0 | J58: =IF(F58="NA", "NA", IF(G58>0, 1, 0)) -> 0 | K58: =IF(F58="NA","NA",IF(H58>2,1,IF(H58>1,0.5,0))) -> 0 | L58: =IF(F58="NA","NA",IF(I58>5, 1, IF(I58>2, 0.5, 0))) -> 0 | M58: =SUMIF(J58:L58,"<>#N/A") -> 0 | N58: =IF(F58 = "NA", "NA", 0) -> 0 | O58: =IF(F58 = "NA", "NA", 0) -> 0 | P58: =IF(F58 = "NA", "NA", 0) -> 0 | Q58: =IF(F58 = "NA", "NA", 0) -> 0 | R58: =IF(F58 = "NA", "NA", 0) -> 0 | S58: =SUMIF(N58:R58,"<>#N/A") -> 0
A59: TI.TIS.TIS.027 | E59: iv. By Category | G59: =IF(LEN(TRIM(F59)) = 4, 1, IF(LEN(TRIM(F59)) > 5, LEN(TRIM(F59))-LEN(SUBSTITUTE(TRIM(F59),",",""))+1, 0)) -> 0 | H59: =IF(ISNUMBER(SEARCH($F$2, $F59)), 1, 0) + IF(ISNUMBER(SEARCH($F$2-1, $F59)), 1, 0) + IF(ISNUMBER(SEARCH($F$2-2, $F59)), 1, 0) + IF(ISNUMBER(SEARCH($F$2-3, $F59)), 1, 0) + IF(ISNUMBER(SEARCH($F$2-4, $F59)), 1, 0) -> 0 | I59: =IF(ISNUMBER(SEARCH($F$2, $F59)), 1, 0) + IF(ISNUMBER(SEARCH($F$2-1, $F59)), 1, 0) + IF(ISNUMBER(SEARCH($F$2-2, $F59)), 1, 0) + IF(ISNUMBER(SEARCH($F$2-3, $F59)), 1, 0) + IF(ISNUMBER(SEARCH($F$2-4, $F59)), 1, 0) + IF(ISNUMBER(SEARCH($F$2-5, $F59)), 1, 0) + IF(ISNUMBER(SEARCH($F$2-6, $F59)), 1, 0) + IF(ISNUMBER(SEARCH($F$2-7, $F59)), 1, 0) + IF(ISNUMBER(SEARCH($F$2-8, $F59)), 1, 0) + IF(ISNUMBER(SEARCH($F$2-9, $F59)), 1, 0) -> 0 | J59: =IF(F59="NA", "NA", IF(G59>0, 1, 0)) -> 0 | K59: =IF(F59="NA","NA",IF(H59>2,1,IF(H59>1,0.5,0))) -> 0 | L59: =IF(F59="NA","NA",IF(I59>5, 1, IF(I59>2, 0.5, 0))) -> 0 | M59: =SUMIF(J59:L59,"<>#N/A") -> 0 | N59: =IF(F59 = "NA", "NA", 0) -> 0 | O59: =IF(F59 = "NA", "NA", 0) -> 0 | P59: =IF(F59 = "NA", "NA", 0) -> 0 | Q59: =IF(F59 = "NA", "NA", 0) -> 0 | R59: =IF(F59 = "NA", "NA", 0) -> 0 | S59: =SUMIF(N59:R59,"<>#N/A") -> 0
A60: TI.TIS.TIS.028 | E60: v. By Country/ Region | G60: =IF(LEN(TRIM(F60)) = 4, 1, IF(LEN(TRIM(F60)) > 5, LEN(TRIM(F60))-LEN(SUBSTITUTE(TRIM(F60),",",""))+1, 0)) -> 0 | H60: =IF(ISNUMBER(SEARCH($F$2, $F60)), 1, 0) + IF(ISNUMBER(SEARCH($F$2-1, $F60)), 1, 0) + IF(ISNUMBER(SEARCH($F$2-2, $F60)), 1, 0) + IF(ISNUMBER(SEARCH($F$2-3, $F60)), 1, 0) + IF(ISNUMBER(SEARCH($F$2-4, $F60)), 1, 0) -> 0 | I60: =IF(ISNUMBER(SEARCH($F$2, $F60)), 1, 0) + IF(ISNUMBER(SEARCH($F$2-1, $F60)), 1, 0) + IF(ISNUMBER(SEARCH($F$2-2, $F60)), 1, 0) + IF(ISNUMBER(SEARCH($F$2-3, $F60)), 1, 0) + IF(ISNUMBER(SEARCH($F$2-4, $F60)), 1, 0) + IF(ISNUMBER(SEARCH($F$2-5, $F60)), 1, 0) + IF(ISNUMBER(SEARCH($F$2-6, $F60)), 1, 0) + IF(ISNUMBER(SEARCH($F$2-7, $F60)), 1, 0) + IF(ISNUMBER(SEARCH($F$2-8, $F60)), 1, 0) + IF(ISNUMBER(SEARCH($F$2-9, $F60)), 1, 0) -> 0 | J60: =IF(F60="NA", "NA", IF(G60>0, 1, 0)) -> 0 | K60: =IF(F60="NA","NA",IF(H60>2,1,IF(H60>1,0.5,0))) -> 0 | L60: =IF(F60="NA","NA",IF(I60>5, 1, IF(I60>2, 0.5, 0))) -> 0 | M60: =SUMIF(J60:L60,"<>#N/A") -> 0 | N60: =IF(F60 = "NA", "NA", 0) -> 0 | O60: =IF(F60 = "NA", "NA", 0) -> 0 | P60: =IF(F60 = "NA", "NA", 0) -> 0 | Q60: =IF(F60 = "NA", "NA", 0) -> 0 | R60: =IF(F60 = "NA", "NA", 0) -> 0 | S60: =SUMIF(N60:R60,"<>#N/A") -> 0
A61: TI.TIS.TIS.029 | E61: vi. By Intra, Extra ^ | F61: NA | G61: =IF(LEN(TRIM(F61)) = 4, 1, IF(LEN(TRIM(F61)) > 5, LEN(TRIM(F61))-LEN(SUBSTITUTE(TRIM(F61),",",""))+1, 0)) -> 0 | H61: =IF(ISNUMBER(SEARCH($F$2, $F61)), 1, 0) + IF(ISNUMBER(SEARCH($F$2-1, $F61)), 1, 0) + IF(ISNUMBER(SEARCH($F$2-2, $F61)), 1, 0) + IF(ISNUMBER(SEARCH($F$2-3, $F61)), 1, 0) + IF(ISNUMBER(SEARCH($F$2-4, $F61)), 1, 0) -> 0 | I61: =IF(ISNUMBER(SEARCH($F$2, $F61)), 1, 0) + IF(ISNUMBER(SEARCH($F$2-1, $F61)), 1, 0) + IF(ISNUMBER(SEARCH($F$2-2, $F61)), 1, 0) + IF(ISNUMBER(SEARCH($F$2-3, $F61)), 1, 0) + IF(ISNUMBER(SEARCH($F$2-4, $F61)), 1, 0) + IF(ISNUMBER(SEARCH($F$2-5, $F61)), 1, 0) + IF(ISNUMBER(SEARCH($F$2-6, $F61)), 1, 0) + IF(ISNUMBER(SEARCH($F$2-7, $F61)), 1, 0) + IF(ISNUMBER(SEARCH($F$2-8, $F61)), 1, 0) + IF(ISNUMBER(SEARCH($F$2-9, $F61)), 1, 0) -> 0 | J61: =IF(F61="NA", "NA", IF(G61>0, 1, 0)) -> NA | K61: =IF(F61="NA","NA",IF(H61>2,1,IF(H61>1,0.5,0))) -> NA | L61: =IF(F61="NA","NA",IF(I61>5, 1, IF(I61>2, 0.5, 0))) -> NA | M61: =SUMIF(J61:L61,"<>#N/A") -> 0 | N61: =IF(F61 = "NA", "NA", 0) -> NA | O61: =IF(F61 = "NA", "NA", 0) -> NA | P61: =IF(F61 = "NA", "NA", 0) -> NA | Q61: =IF(F61 = "NA", "NA", 0) -> NA | R61: =IF(F61 = "NA", "NA", 0) -> NA | S61: =SUMIF(N61:R61,"<>#N/A") -> 0 | T61: NA | U61: NA
A62: TI.INV.FDI.001 | C62: Investment | D62: Net FDI Inflows AMS: (2) ASEANStats: (4) | E62: i. Total | G62: =IF(LEN(TRIM(F62)) = 4, 1, IF(LEN(TRIM(F62)) > 5, LEN(TRIM(F62))-LEN(SUBSTITUTE(TRIM(F62),",",""))+1, 0)) -> 0 | H62: =IF(ISNUMBER(SEARCH($F$2, $F62)), 1, 0) + IF(ISNUMBER(SEARCH($F$2-1, $F62)), 1, 0) + IF(ISNUMBER(SEARCH($F$2-2, $F62)), 1, 0) + IF(ISNUMBER(SEARCH($F$2-3, $F62)), 1, 0) + IF(ISNUMBER(SEARCH($F$2-4, $F62)), 1, 0) -> 0 | I62: =IF(ISNUMBER(SEARCH($F$2, $F62)), 1, 0) + IF(ISNUMBER(SEARCH($F$2-1, $F62)), 1, 0) + IF(ISNUMBER(SEARCH($F$2-2, $F62)), 1, 0) + IF(ISNUMBER(SEARCH($F$2-3, $F62)), 1, 0) + IF(ISNUMBER(SEARCH($F$2-4, $F62)), 1, 0) + IF(ISNUMBER(SEARCH($F$2-5, $F62)), 1, 0) + IF(ISNUMBER(SEARCH($F$2-6, $F62)), 1, 0) + IF(ISNUMBER(SEARCH($F$2-7, $F62)), 1, 0) + IF(ISNUMBER(SEARCH($F$2-8, $F62)), 1, 0) + IF(ISNUMBER(SEARCH($F$2-9, $F62)), 1, 0) -> 0 | J62: =IF(F62="NA", "NA", IF(G62>0, 1, 0)) -> 0 | K62: =IF(F62="NA","NA",IF(H62>2,1,IF(H62>1,0.5,0))) -> 0 | L62: =IF(F62="NA","NA",IF(I62>5, 1, IF(I62>2, 0.5, 0))) -> 0 | M62: =SUMIF(J62:L62,"<>#N/A") -> 0 | N62: =IF(F62 = "NA", "NA", 0) -> 0 | O62: =IF(F62 = "NA", "NA", 0) -> 0 | P62: =IF(F62 = "NA", "NA", 0) -> 0 | Q62: =IF(F62 = "NA", "NA", 0) -> 0 | R62: =IF(F62 = "NA", "NA", 0) -> 0 | S62: =SUMIF(N62:R62,"<>#N/A") -> 0
A63: TI.INV.FDI.030 | E63: ii. By Sources | G63: =IF(LEN(TRIM(F63)) = 4, 1, IF(LEN(TRIM(F63)) > 5, LEN(TRIM(F63))-LEN(SUBSTITUTE(TRIM(F63),",",""))+1, 0)) -> 0 | H63: =IF(ISNUMBER(SEARCH($F$2, $F63)), 1, 0) + IF(ISNUMBER(SEARCH($F$2-1, $F63)), 1, 0) + IF(ISNUMBER(SEARCH($F$2-2, $F63)), 1, 0) + IF(ISNUMBER(SEARCH($F$2-3, $F63)), 1, 0) + IF(ISNUMBER(SEARCH($F$2-4, $F63)), 1, 0) -> 0 | I63: =IF(ISNUMBER(SEARCH($F$2, $F63)), 1, 0) + IF(ISNUMBER(SEARCH($F$2-1, $F63)), 1, 0) + IF(ISNUMBER(SEARCH($F$2-2, $F63)), 1, 0) + IF(ISNUMBER(SEARCH($F$2-3, $F63)), 1, 0) + IF(ISNUMBER(SEARCH($F$2-4, $F63)), 1, 0) + IF(ISNUMBER(SEARCH($F$2-5, $F63)), 1, 0) + IF(ISNUMBER(SEARCH($F$2-6, $F63)), 1, 0) + IF(ISNUMBER(SEARCH($F$2-7, $F63)), 1, 0) + IF(ISNUMBER(SEARCH($F$2-8, $F63)), 1, 0) + IF(ISNUMBER(SEARCH($F$2-9, $F63)), 1, 0) -> 0 | J63: =IF(F63="NA", "NA", IF(G63>0, 1, 0)) -> 0 | K63: =IF(F63="NA","NA",IF(H63>2,1,IF(H63>1,0.5,0))) -> 0 | L63: =IF(F63="NA","NA",IF(I63>5, 1, IF(I63>2, 0.5, 0))) -> 0 | M63: =SUMIF(J63:L63,"<>#N/A") -> 0 | N63: =IF(F63 = "NA", "NA", 0) -> 0 | O63: =IF(F63 = "NA", "NA", 0) -> 0 | P63: =IF(F63 = "NA", "NA", 0) -> 0 | Q63: =IF(F63 = "NA", "NA", 0) -> 0 | R63: =IF(F63 = "NA", "NA", 0) -> 0 | S63: =SUMIF(N63:R63,"<>#N/A") -> 0
A64: TI.INV.FDI.031 | E64: iii. By Sector/ Activities^ | F64: NA | G64: =IF(LEN(TRIM(F64)) = 4, 1, IF(LEN(TRIM(F64)) > 5, LEN(TRIM(F64))-LEN(SUBSTITUTE(TRIM(F64),",",""))+1, 0)) -> 0 | H64: =IF(ISNUMBER(SEARCH($F$2, $F64)), 1, 0) + IF(ISNUMBER(SEARCH($F$2-1, $F64)), 1, 0) + IF(ISNUMBER(SEARCH($F$2-2, $F64)), 1, 0) + IF(ISNUMBER(SEARCH($F$2-3, $F64)), 1, 0) + IF(ISNUMBER(SEARCH($F$2-4, $F64)), 1, 0) -> 0 | I64: =IF(ISNUMBER(SEARCH($F$2, $F64)), 1, 0) + IF(ISNUMBER(SEARCH($F$2-1, $F64)), 1, 0) + IF(ISNUMBER(SEARCH($F$2-2, $F64)), 1, 0) + IF(ISNUMBER(SEARCH($F$2-3, $F64)), 1, 0) + IF(ISNUMBER(SEARCH($F$2-4, $F64)), 1, 0) + IF(ISNUMBER(SEARCH($F$2-5, $F64)), 1, 0) + IF(ISNUMBER(SEARCH($F$2-6, $F64)), 1, 0) + IF(ISNUMBER(SEARCH($F$2-7, $F64)), 1, 0) + IF(ISNUMBER(SEARCH($F$2-8, $F64)), 1, 0) + IF(ISNUMBER(SEARCH($F$2-9, $F64)), 1, 0) -> 0 | J64: =IF(F64="NA", "NA", IF(G64>0, 1, 0)) -> NA | K64: =IF(F64="NA","NA",IF(H64>2,1,IF(H64>1,0.5,0))) -> NA | L64: =IF(F64="NA","NA",IF(I64>5, 1, IF(I64>2, 0.5, 0))) -> NA | M64: =SUMIF(J64:L64,"<>#N/A") -> 0 | N64: =IF(F64 = "NA", "NA", 0) -> NA | O64: =IF(F64 = "NA", "NA", 0) -> NA | P64: =IF(F64 = "NA", "NA", 0) -> NA | Q64: =IF(F64 = "NA", "NA", 0) -> NA | R64: =IF(F64 = "NA", "NA", 0) -> NA | S64: =SUMIF(N64:R64,"<>#N/A") -> 0 | T64: NA | U64: NA
A65: TI.INV.FDI.032 | E65: iv. By Intra, Extra ^ | F65: NA | G65: =IF(LEN(TRIM(F65)) = 4, 1, IF(LEN(TRIM(F65)) > 5, LEN(TRIM(F65))-LEN(SUBSTITUTE(TRIM(F65),",",""))+1, 0)) -> 0 | H65: =IF(ISNUMBER(SEARCH($F$2, $F65)), 1, 0) + IF(ISNUMBER(SEARCH($F$2-1, $F65)), 1, 0) + IF(ISNUMBER(SEARCH($F$2-2, $F65)), 1, 0) + IF(ISNUMBER(SEARCH($F$2-3, $F65)), 1, 0) + IF(ISNUMBER(SEARCH($F$2-4, $F65)), 1, 0) -> 0 | I65: =IF(ISNUMBER(SEARCH($F$2, $F65)), 1, 0) + IF(ISNUMBER(SEARCH($F$2-1, $F65)), 1, 0) + IF(ISNUMBER(SEARCH($F$2-2, $F65)), 1, 0) + IF(ISNUMBER(SEARCH($F$2-3, $F65)), 1, 0) + IF(ISNUMBER(SEARCH($F$2-4, $F65)), 1, 0) + IF(ISNUMBER(SEARCH($F$2-5, $F65)), 1, 0) + IF(ISNUMBER(SEARCH($F$2-6, $F65)), 1, 0) + IF(ISNUMBER(SEARCH($F$2-7, $F65)), 1, 0) + IF(ISNUMBER(SEARCH($F$2-8, $F65)), 1, 0) + IF(ISNUMBER(SEARCH($F$2-9, $F65)), 1, 0) -> 0 | J65: =IF(F65="NA", "NA", IF(G65>0, 1, 0)) -> NA | K65: =IF(F65="NA","NA",IF(H65>2,1,IF(H65>1,0.5,0))) -> NA | L65: =IF(F65="NA","NA",IF(I65>5, 1, IF(I65>2, 0.5, 0))) -> NA | M65: =SUMIF(J65:L65,"<>#N/A") -> 0 | N65: =IF(F65 = "NA", "NA", 0) -> NA | O65: =IF(F65 = "NA", "NA", 0) -> NA | P65: =IF(F65 = "NA", "NA", 0) -> NA | Q65: =IF(F65 = "NA", "NA", 0) -> NA | R65: =IF(F65 = "NA", "NA", 0) -> NA | S65: =SUMIF(N65:R65,"<>#N/A") -> 0 | T65: NA | U65: NA
A66: CN.TRS.TOA.001 | B66: Connectivity and Environment Indicators | C66: Tourism | D66: Tourist Arrivals AMS: (2) ASEANStats: (3) | E66: i. Total | G66: =IF(LEN(TRIM(F66)) = 4, 1, IF(LEN(TRIM(F66)) > 5, LEN(TRIM(F66))-LEN(SUBSTITUTE(TRIM(F66),",",""))+1, 0)) -> 0 | H66: =IF(ISNUMBER(SEARCH($F$2, $F66)), 1, 0) + IF(ISNUMBER(SEARCH($F$2-1, $F66)), 1, 0) + IF(ISNUMBER(SEARCH($F$2-2, $F66)), 1, 0) + IF(ISNUMBER(SEARCH($F$2-3, $F66)), 1, 0) + IF(ISNUMBER(SEARCH($F$2-4, $F66)), 1, 0) -> 0 | I66: =IF(ISNUMBER(SEARCH($F$2, $F66)), 1, 0) + IF(ISNUMBER(SEARCH($F$2-1, $F66)), 1, 0) + IF(ISNUMBER(SEARCH($F$2-2, $F66)), 1, 0) + IF(ISNUMBER(SEARCH($F$2-3, $F66)), 1, 0) + IF(ISNUMBER(SEARCH($F$2-4, $F66)), 1, 0) + IF(ISNUMBER(SEARCH($F$2-5, $F66)), 1, 0) + IF(ISNUMBER(SEARCH($F$2-6, $F66)), 1, 0) + IF(ISNUMBER(SEARCH($F$2-7, $F66)), 1, 0) + IF(ISNUMBER(SEARCH($F$2-8, $F66)), 1, 0) + IF(ISNUMBER(SEARCH($F$2-9, $F66)), 1, 0) -> 0 | J66: =IF(F66="NA", "NA", IF(G66>0, 1, 0)) -> 0 | K66: =IF(F66="NA","NA",IF(H66>2,1,IF(H66>1,0.5,0))) -> 0 | L66: =IF(F66="NA","NA",IF(I66>5, 1, IF(I66>2, 0.5, 0))) -> 0 | M66: =SUMIF(J66:L66,"<>#N/A") -> 0 | N66: =IF(F66 = "NA", "NA", 0) -> 0 | O66: =IF(F66 = "NA", "NA", 0) -> 0 | P66: =IF(F66 = "NA", "NA", 0) -> 0 | Q66: =IF(F66 = "NA", "NA", 0) -> 0 | R66: =IF(F66 = "NA", "NA", 0) -> 0 | S66: =SUMIF(N66:R66,"<>#N/A") -> 0
A67: CN.TRS.TOA.033 | E67: ii. By Country/ Region | G67: =IF(LEN(TRIM(F67)) = 4, 1, IF(LEN(TRIM(F67)) > 5, LEN(TRIM(F67))-LEN(SUBSTITUTE(TRIM(F67),",",""))+1, 0)) -> 0 | H67: =IF(ISNUMBER(SEARCH($F$2, $F67)), 1, 0) + IF(ISNUMBER(SEARCH($F$2-1, $F67)), 1, 0) + IF(ISNUMBER(SEARCH($F$2-2, $F67)), 1, 0) + IF(ISNUMBER(SEARCH($F$2-3, $F67)), 1, 0) + IF(ISNUMBER(SEARCH($F$2-4, $F67)), 1, 0) -> 0 | I67: =IF(ISNUMBER(SEARCH($F$2, $F67)), 1, 0) + IF(ISNUMBER(SEARCH($F$2-1, $F67)), 1, 0) + IF(ISNUMBER(SEARCH($F$2-2, $F67)), 1, 0) + IF(ISNUMBER(SEARCH($F$2-3, $F67)), 1, 0) + IF(ISNUMBER(SEARCH($F$2-4, $F67)), 1, 0) + IF(ISNUMBER(SEARCH($F$2-5, $F67)), 1, 0) + IF(ISNUMBER(SEARCH($F$2-6, $F67)), 1, 0) + IF(ISNUMBER(SEARCH($F$2-7, $F67)), 1, 0) + IF(ISNUMBER(SEARCH($F$2-8, $F67)), 1, 0) + IF(ISNUMBER(SEARCH($F$2-9, $F67)), 1, 0) -> 0 | J67: =IF(F67="NA", "NA", IF(G67>0, 1, 0)) -> 0 | K67: =IF(F67="NA","NA",IF(H67>2,1,IF(H67>1,0.5,0))) -> 0 | L67: =IF(F67="NA","NA",IF(I67>5, 1, IF(I67>2, 0.5, 0))) -> 0 | M67: =SUMIF(J67:L67,"<>#N/A") -> 0 | N67: =IF(F67 = "NA", "NA", 0) -> 0 | O67: =IF(F67 = "NA", "NA", 0) -> 0 | P67: =IF(F67 = "NA", "NA", 0) -> 0 | Q67: =IF(F67 = "NA", "NA", 0) -> 0 | R67: =IF(F67 = "NA", "NA", 0) -> 0 | S67: =SUMIF(N67:R67,"<>#N/A") -> 0
A68: CN.TRS.TOA.034 | E68: iii. By Intra, Extra ^ | F68: NA | G68: =IF(LEN(TRIM(F68)) = 4, 1, IF(LEN(TRIM(F68)) > 5, LEN(TRIM(F68))-LEN(SUBSTITUTE(TRIM(F68),",",""))+1, 0)) -> 0 | H68: =IF(ISNUMBER(SEARCH($F$2, $F68)), 1, 0) + IF(ISNUMBER(SEARCH($F$2-1, $F68)), 1, 0) + IF(ISNUMBER(SEARCH($F$2-2, $F68)), 1, 0) + IF(ISNUMBER(SEARCH($F$2-3, $F68)), 1, 0) + IF(ISNUMBER(SEARCH($F$2-4, $F68)), 1, 0) -> 0 | I68: =IF(ISNUMBER(SEARCH($F$2, $F68)), 1, 0) + IF(ISNUMBER(SEARCH($F$2-1, $F68)), 1, 0) + IF(ISNUMBER(SEARCH($F$2-2, $F68)), 1, 0) + IF(ISNUMBER(SEARCH($F$2-3, $F68)), 1, 0) + IF(ISNUMBER(SEARCH($F$2-4, $F68)), 1, 0) + IF(ISNUMBER(SEARCH($F$2-5, $F68)), 1, 0) + IF(ISNUMBER(SEARCH($F$2-6, $F68)), 1, 0) + IF(ISNUMBER(SEARCH($F$2-7, $F68)), 1, 0) + IF(ISNUMBER(SEARCH($F$2-8, $F68)), 1, 0) + IF(ISNUMBER(SEARCH($F$2-9, $F68)), 1, 0) -> 0 | J68: =IF(F68="NA", "NA", IF(G68>0, 1, 0)) -> NA | K68: =IF(F68="NA","NA",IF(H68>2,1,IF(H68>1,0.5,0))) -> NA | L68: =IF(F68="NA","NA",IF(I68>5, 1, IF(I68>2, 0.5, 0))) -> NA | M68: =SUMIF(J68:L68,"<>#N/A") -> 0 | N68: =IF(F68 = "NA", "NA", 0) -> NA | O68: =IF(F68 = "NA", "NA", 0) -> NA | P68: =IF(F68 = "NA", "NA", 0) -> NA | Q68: =IF(F68 = "NA", "NA", 0) -> NA | R68: =IF(F68 = "NA", "NA", 0) -> NA | S68: =SUMIF(N68:R68,"<>#N/A") -> 0 | T68: NA | U68: NA
A69: CN.TRP.PST.035 | C69: Transport | D69: Passenger Traffic (1) | E69: By Mode of Transport (At Least 2 Modes) | G69: =IF(LEN(TRIM(F69)) = 4, 1, IF(LEN(TRIM(F69)) > 5, LEN(TRIM(F69))-LEN(SUBSTITUTE(TRIM(F69),",",""))+1, 0)) -> 0 | H69: =IF(ISNUMBER(SEARCH($F$2, $F69)), 1, 0) + IF(ISNUMBER(SEARCH($F$2-1, $F69)), 1, 0) + IF(ISNUMBER(SEARCH($F$2-2, $F69)), 1, 0) + IF(ISNUMBER(SEARCH($F$2-3, $F69)), 1, 0) + IF(ISNUMBER(SEARCH($F$2-4, $F69)), 1, 0) -> 0 | I69: =IF(ISNUMBER(SEARCH($F$2, $F69)), 1, 0) + IF(ISNUMBER(SEARCH($F$2-1, $F69)), 1, 0) + IF(ISNUMBER(SEARCH($F$2-2, $F69)), 1, 0) + IF(ISNUMBER(SEARCH($F$2-3, $F69)), 1, 0) + IF(ISNUMBER(SEARCH($F$2-4, $F69)), 1, 0) + IF(ISNUMBER(SEARCH($F$2-5, $F69)), 1, 0) + IF(ISNUMBER(SEARCH($F$2-6, $F69)), 1, 0) + IF(ISNUMBER(SEARCH($F$2-7, $F69)), 1, 0) + IF(ISNUMBER(SEARCH($F$2-8, $F69)), 1, 0) + IF(ISNUMBER(SEARCH($F$2-9, $F69)), 1, 0) -> 0 | J69: =IF(F69="NA", "NA", IF(G69>0, 1, 0)) -> 0 | K69: =IF(F69="NA","NA",IF(H69>2,1,IF(H69>1,0.5,0))) -> 0 | L69: =IF(F69="NA","NA",IF(I69>5, 1, IF(I69>2, 0.5, 0))) -> 0 | M69: =SUMIF(J69:L69,"<>#N/A") -> 0 | N69: =IF(F69 = "NA", "NA", 0) -> 0 | O69: =IF(F69 = "NA", "NA", 0) -> 0 | P69: =IF(F69 = "NA", "NA", 0) -> 0 | Q69: =IF(F69 = "NA", "NA", 0) -> 0 | R69: =IF(F69 = "NA", "NA", 0) -> 0 | S69: =SUMIF(N69:R69,"<>#N/A") -> 0
A70: CN.TRP.FRV.035 | D70: Freight Volumes (1) | E70: By Mode of Transport (At Least 2 Modes) | G70: =IF(LEN(TRIM(F70)) = 4, 1, IF(LEN(TRIM(F70)) > 5, LEN(TRIM(F70))-LEN(SUBSTITUTE(TRIM(F70),",",""))+1, 0)) -> 0 | H70: =IF(ISNUMBER(SEARCH($F$2, $F70)), 1, 0) + IF(ISNUMBER(SEARCH($F$2-1, $F70)), 1, 0) + IF(ISNUMBER(SEARCH($F$2-2, $F70)), 1, 0) + IF(ISNUMBER(SEARCH($F$2-3, $F70)), 1, 0) + IF(ISNUMBER(SEARCH($F$2-4, $F70)), 1, 0) -> 0 | I70: =IF(ISNUMBER(SEARCH($F$2, $F70)), 1, 0) + IF(ISNUMBER(SEARCH($F$2-1, $F70)), 1, 0) + IF(ISNUMBER(SEARCH($F$2-2, $F70)), 1, 0) + IF(ISNUMBER(SEARCH($F$2-3, $F70)), 1, 0) + IF(ISNUMBER(SEARCH($F$2-4, $F70)), 1, 0) + IF(ISNUMBER(SEARCH($F$2-5, $F70)), 1, 0) + IF(ISNUMBER(SEARCH($F$2-6, $F70)), 1, 0) + IF(ISNUMBER(SEARCH($F$2-7, $F70)), 1, 0) + IF(ISNUMBER(SEARCH($F$2-8, $F70)), 1, 0) + IF(ISNUMBER(SEARCH($F$2-9, $F70)), 1, 0) -> 0 | J70: =IF(F70="NA", "NA", IF(G70>0, 1, 0)) -> 0 | K70: =IF(F70="NA","NA",IF(H70>2,1,IF(H70>1,0.5,0))) -> 0 | L70: =IF(F70="NA","NA",IF(I70>5, 1, IF(I70>2, 0.5, 0))) -> 0 | M70: =SUMIF(J70:L70,"<>#N/A") -> 0 | N70: =IF(F70 = "NA", "NA", 0) -> 0 | O70: =IF(F70 = "NA", "NA", 0) -> 0 | P70: =IF(F70 = "NA", "NA", 0) -> 0 | Q70: =IF(F70 = "NA", "NA", 0) -> 0 | R70: =IF(F70 = "NA", "NA", 0) -> 0 | S70: =SUMIF(N70:R70,"<>#N/A") -> 0
A71: CN.TRP.DRR.000 | D71: Death Rate Due to Road Traffic Injuries (1) | G71: =IF(LEN(TRIM(F71)) = 4, 1, IF(LEN(TRIM(F71)) > 5, LEN(TRIM(F71))-LEN(SUBSTITUTE(TRIM(F71),",",""))+1, 0)) -> 0 | H71: =IF(ISNUMBER(SEARCH($F$2, $F71)), 1, 0) + IF(ISNUMBER(SEARCH($F$2-1, $F71)), 1, 0) + IF(ISNUMBER(SEARCH($F$2-2, $F71)), 1, 0) + IF(ISNUMBER(SEARCH($F$2-3, $F71)), 1, 0) + IF(ISNUMBER(SEARCH($F$2-4, $F71)), 1, 0) -> 0 | I71: =IF(ISNUMBER(SEARCH($F$2, $F71)), 1, 0) + IF(ISNUMBER(SEARCH($F$2-1, $F71)), 1, 0) + IF(ISNUMBER(SEARCH($F$2-2, $F71)), 1, 0) + IF(ISNUMBER(SEARCH($F$2-3, $F71)), 1, 0) + IF(ISNUMBER(SEARCH($F$2-4, $F71)), 1, 0) + IF(ISNUMBER(SEARCH($F$2-5, $F71)), 1, 0) + IF(ISNUMBER(SEARCH($F$2-6, $F71)), 1, 0) + IF(ISNUMBER(SEARCH($F$2-7, $F71)), 1, 0) + IF(ISNUMBER(SEARCH($F$2-8, $F71)), 1, 0) + IF(ISNUMBER(SEARCH($F$2-9, $F71)), 1, 0) -> 0 | J71: =IF(F71="NA", "NA", IF(G71>0, 1, 0)) -> 0 | K71: =IF(F71="NA","NA",IF(H71>2,1,IF(H71>1,0.5,0))) -> 0 | L71: =IF(F71="NA","NA",IF(I71>5, 1, IF(I71>2, 0.5, 0))) -> 0 | M71: =SUMIF(J71:L71,"<>#N/A") -> 0 | N71: =IF(F71 = "NA", "NA", 0) -> 0 | O71: =IF(F71 = "NA", "NA", 0) -> 0 | P71: =IF(F71 = "NA", "NA", 0) -> 0 | Q71: =IF(F71 = "NA", "NA", 0) -> 0 | R71: =IF(F71 = "NA", "NA", 0) -> 0 | S71: =SUMIF(N71:R71,"<>#N/A") -> 0
A72: CN.COM.INT.000 | C72: Communications | D72: Proportion of Individuals Using Internet (1) | G72: =IF(LEN(TRIM(F72)) = 4, 1, IF(LEN(TRIM(F72)) > 5, LEN(TRIM(F72))-LEN(SUBSTITUTE(TRIM(F72),",",""))+1, 0)) -> 0 | H72: =IF(ISNUMBER(SEARCH($F$2, $F72)), 1, 0) + IF(ISNUMBER(SEARCH($F$2-1, $F72)), 1, 0) + IF(ISNUMBER(SEARCH($F$2-2, $F72)), 1, 0) + IF(ISNUMBER(SEARCH($F$2-3, $F72)), 1, 0) + IF(ISNUMBER(SEARCH($F$2-4, $F72)), 1, 0) -> 0 | I72: =IF(ISNUMBER(SEARCH($F$2, $F72)), 1, 0) + IF(ISNUMBER(SEARCH($F$2-1, $F72)), 1, 0) + IF(ISNUMBER(SEARCH($F$2-2, $F72)), 1, 0) + IF(ISNUMBER(SEARCH($F$2-3, $F72)), 1, 0) + IF(ISNUMBER(SEARCH($F$2-4, $F72)), 1, 0) + IF(ISNUMBER(SEARCH($F$2-5, $F72)), 1, 0) + IF(ISNUMBER(SEARCH($F$2-6, $F72)), 1, 0) + IF(ISNUMBER(SEARCH($F$2-7, $F72)), 1, 0) + IF(ISNUMBER(SEARCH($F$2-8, $F72)), 1, 0) + IF(ISNUMBER(SEARCH($F$2-9, $F72)), 1, 0) -> 0 | J72: =IF(F72="NA", "NA", IF(G72>0, 1, 0)) -> 0 | K72: =IF(F72="NA","NA",IF(H72>2,1,IF(H72>1,0.5,0))) -> 0 | L72: =IF(F72="NA","NA",IF(I72>5, 1, IF(I72>2, 0.5, 0))) -> 0 | M72: =SUMIF(J72:L72,"<>#N/A") -> 0 | N72: =IF(F72 = "NA", "NA", 0) -> 0 | O72: =IF(F72 = "NA", "NA", 0) -> 0 | P72: =IF(F72 = "NA", "NA", 0) -> 0 | Q72: =IF(F72 = "NA", "NA", 0) -> 0 | R72: =IF(F72 = "NA", "NA", 0) -> 0 | S72: =SUMIF(N72:R72,"<>#N/A") -> 0
A73: CN.COM.BRO.000 | D73: Fixed Internet Broadband Subscriptions Per 100 Population (1) | G73: =IF(LEN(TRIM(F73)) = 4, 1, IF(LEN(TRIM(F73)) > 5, LEN(TRIM(F73))-LEN(SUBSTITUTE(TRIM(F73),",",""))+1, 0)) -> 0 | H73: =IF(ISNUMBER(SEARCH($F$2, $F73)), 1, 0) + IF(ISNUMBER(SEARCH($F$2-1, $F73)), 1, 0) + IF(ISNUMBER(SEARCH($F$2-2, $F73)), 1, 0) + IF(ISNUMBER(SEARCH($F$2-3, $F73)), 1, 0) + IF(ISNUMBER(SEARCH($F$2-4, $F73)), 1, 0) -> 0 | I73: =IF(ISNUMBER(SEARCH($F$2, $F73)), 1, 0) + IF(ISNUMBER(SEARCH($F$2-1, $F73)), 1, 0) + IF(ISNUMBER(SEARCH($F$2-2, $F73)), 1, 0) + IF(ISNUMBER(SEARCH($F$2-3, $F73)), 1, 0) + IF(ISNUMBER(SEARCH($F$2-4, $F73)), 1, 0) + IF(ISNUMBER(SEARCH($F$2-5, $F73)), 1, 0) + IF(ISNUMBER(SEARCH($F$2-6, $F73)), 1, 0) + IF(ISNUMBER(SEARCH($F$2-7, $F73)), 1, 0) + IF(ISNUMBER(SEARCH($F$2-8, $F73)), 1, 0) + IF(ISNUMBER(SEARCH($F$2-9, $F73)), 1, 0) -> 0 | J73: =IF(F73="NA", "NA", IF(G73>0, 1, 0)) -> 0 | K73: =IF(F73="NA","NA",IF(H73>2,1,IF(H73>1,0.5,0))) -> 0 | L73: =IF(F73="NA","NA",IF(I73>5, 1, IF(I73>2, 0.5, 0))) -> 0 | M73: =SUMIF(J73:L73,"<>#N/A") -> 0 | N73: =IF(F73 = "NA", "NA", 0) -> 0 | O73: =IF(F73 = "NA", "NA", 0) -> 0 | P73: =IF(F73 = "NA", "NA", 0) -> 0 | Q73: =IF(F73 = "NA", "NA", 0) -> 0 | R73: =IF(F73 = "NA", "NA", 0) -> 0 | S73: =SUMIF(N73:R73,"<>#N/A") -> 0
A74: CN.COM.PPM.000 | D74: Proportion of Population Covered by a Mobile Network (1) | G74: =IF(LEN(TRIM(F74)) = 4, 1, IF(LEN(TRIM(F74)) > 5, LEN(TRIM(F74))-LEN(SUBSTITUTE(TRIM(F74),",",""))+1, 0)) -> 0 | H74: =IF(ISNUMBER(SEARCH($F$2, $F74)), 1, 0) + IF(ISNUMBER(SEARCH($F$2-1, $F74)), 1, 0) + IF(ISNUMBER(SEARCH($F$2-2, $F74)), 1, 0) + IF(ISNUMBER(SEARCH($F$2-3, $F74)), 1, 0) + IF(ISNUMBER(SEARCH($F$2-4, $F74)), 1, 0) -> 0 | I74: =IF(ISNUMBER(SEARCH($F$2, $F74)), 1, 0) + IF(ISNUMBER(SEARCH($F$2-1, $F74)), 1, 0) + IF(ISNUMBER(SEARCH($F$2-2, $F74)), 1, 0) + IF(ISNUMBER(SEARCH($F$2-3, $F74)), 1, 0) + IF(ISNUMBER(SEARCH($F$2-4, $F74)), 1, 0) + IF(ISNUMBER(SEARCH($F$2-5, $F74)), 1, 0) + IF(ISNUMBER(SEARCH($F$2-6, $F74)), 1, 0) + IF(ISNUMBER(SEARCH($F$2-7, $F74)), 1, 0) + IF(ISNUMBER(SEARCH($F$2-8, $F74)), 1, 0) + IF(ISNUMBER(SEARCH($F$2-9, $F74)), 1, 0) -> 0 | J74: =IF(F74="NA", "NA", IF(G74>0, 1, 0)) -> 0 | K74: =IF(F74="NA","NA",IF(H74>2,1,IF(H74>1,0.5,0))) -> 0 | L74: =IF(F74="NA","NA",IF(I74>5, 1, IF(I74>2, 0.5, 0))) -> 0 | M74: =SUMIF(J74:L74,"<>#N/A") -> 0 | N74: =IF(F74 = "NA", "NA", 0) -> 0 | O74: =IF(F74 = "NA", "NA", 0) -> 0 | P74: =IF(F74 = "NA", "NA", 0) -> 0 | Q74: =IF(F74 = "NA", "NA", 0) -> 0 | R74: =IF(F74 = "NA", "NA", 0) -> 0 | S74: =SUMIF(N74:R74,"<>#N/A") -> 0
A75: CN.ACW.PPS.000 | C75: Access to Clean Water, Sanitation and Electricity | D75: Proportion of Population with Access to Safe Drinking Water (1) | G75: =IF(LEN(TRIM(F75)) = 4, 1, IF(LEN(TRIM(F75)) > 5, LEN(TRIM(F75))-LEN(SUBSTITUTE(TRIM(F75),",",""))+1, 0)) -> 0 | H75: =IF(ISNUMBER(SEARCH($F$2, $F75)), 1, 0) + IF(ISNUMBER(SEARCH($F$2-1, $F75)), 1, 0) + IF(ISNUMBER(SEARCH($F$2-2, $F75)), 1, 0) + IF(ISNUMBER(SEARCH($F$2-3, $F75)), 1, 0) + IF(ISNUMBER(SEARCH($F$2-4, $F75)), 1, 0) -> 0 | I75: =IF(ISNUMBER(SEARCH($F$2, $F75)), 1, 0) + IF(ISNUMBER(SEARCH($F$2-1, $F75)), 1, 0) + IF(ISNUMBER(SEARCH($F$2-2, $F75)), 1, 0) + IF(ISNUMBER(SEARCH($F$2-3, $F75)), 1, 0) + IF(ISNUMBER(SEARCH($F$2-4, $F75)), 1, 0) + IF(ISNUMBER(SEARCH($F$2-5, $F75)), 1, 0) + IF(ISNUMBER(SEARCH($F$2-6, $F75)), 1, 0) + IF(ISNUMBER(SEARCH($F$2-7, $F75)), 1, 0) + IF(ISNUMBER(SEARCH($F$2-8, $F75)), 1, 0) + IF(ISNUMBER(SEARCH($F$2-9, $F75)), 1, 0) -> 0 | J75: =IF(F75="NA", "NA", IF(G75>0, 1, 0)) -> 0 | K75: =IF(F75="NA","NA",IF(H75>2,1,IF(H75>1,0.5,0))) -> 0 | L75: =IF(F75="NA","NA",IF(I75>5, 1, IF(I75>2, 0.5, 0))) -> 0 | M75: =SUMIF(J75:L75,"<>#N/A") -> 0 | N75: =IF(F75 = "NA", "NA", 0) -> 0 | O75: =IF(F75 = "NA", "NA", 0) -> 0 | P75: =IF(F75 = "NA", "NA", 0) -> 0 | Q75: =IF(F75 = "NA", "NA", 0) -> 0 | R75: =IF(F75 = "NA", "NA", 0) -> 0 | S75: =SUMIF(N75:R75,"<>#N/A") -> 0
A76: CN.ACW.PAI.000 | D76: Proportion of Population with Access to Improved Sanitation (1) | G76: =IF(LEN(TRIM(F76)) = 4, 1, IF(LEN(TRIM(F76)) > 5, LEN(TRIM(F76))-LEN(SUBSTITUTE(TRIM(F76),",",""))+1, 0)) -> 0 | H76: =IF(ISNUMBER(SEARCH($F$2, $F76)), 1, 0) + IF(ISNUMBER(SEARCH($F$2-1, $F76)), 1, 0) + IF(ISNUMBER(SEARCH($F$2-2, $F76)), 1, 0) + IF(ISNUMBER(SEARCH($F$2-3, $F76)), 1, 0) + IF(ISNUMBER(SEARCH($F$2-4, $F76)), 1, 0) -> 0 | I76: =IF(ISNUMBER(SEARCH($F$2, $F76)), 1, 0) + IF(ISNUMBER(SEARCH($F$2-1, $F76)), 1, 0) + IF(ISNUMBER(SEARCH($F$2-2, $F76)), 1, 0) + IF(ISNUMBER(SEARCH($F$2-3, $F76)), 1, 0) + IF(ISNUMBER(SEARCH($F$2-4, $F76)), 1, 0) + IF(ISNUMBER(SEARCH($F$2-5, $F76)), 1, 0) + IF(ISNUMBER(SEARCH($F$2-6, $F76)), 1, 0) + IF(ISNUMBER(SEARCH($F$2-7, $F76)), 1, 0) + IF(ISNUMBER(SEARCH($F$2-8, $F76)), 1, 0) + IF(ISNUMBER(SEARCH($F$2-9, $F76)), 1, 0) -> 0 | J76: =IF(F76="NA", "NA", IF(G76>0, 1, 0)) -> 0 | K76: =IF(F76="NA","NA",IF(H76>2,1,IF(H76>1,0.5,0))) -> 0 | L76: =IF(F76="NA","NA",IF(I76>5, 1, IF(I76>2, 0.5, 0))) -> 0 | M76: =SUMIF(J76:L76,"<>#N/A") -> 0 | N76: =IF(F76 = "NA", "NA", 0) -> 0 | O76: =IF(F76 = "NA", "NA", 0) -> 0 | P76: =IF(F76 = "NA", "NA", 0) -> 0 | Q76: =IF(F76 = "NA", "NA", 0) -> 0 | R76: =IF(F76 = "NA", "NA", 0) -> 0 | S76: =SUMIF(N76:R76,"<>#N/A") -> 0
A77: CN.ACW.PPE.000 | D77: Proportion of Population with Access to Electricity (1) | G77: =IF(LEN(TRIM(F77)) = 4, 1, IF(LEN(TRIM(F77)) > 5, LEN(TRIM(F77))-LEN(SUBSTITUTE(TRIM(F77),",",""))+1, 0)) -> 0 | H77: =IF(ISNUMBER(SEARCH($F$2, $F77)), 1, 0) + IF(ISNUMBER(SEARCH($F$2-1, $F77)), 1, 0) + IF(ISNUMBER(SEARCH($F$2-2, $F77)), 1, 0) + IF(ISNUMBER(SEARCH($F$2-3, $F77)), 1, 0) + IF(ISNUMBER(SEARCH($F$2-4, $F77)), 1, 0) -> 0 | I77: =IF(ISNUMBER(SEARCH($F$2, $F77)), 1, 0) + IF(ISNUMBER(SEARCH($F$2-1, $F77)), 1, 0) + IF(ISNUMBER(SEARCH($F$2-2, $F77)), 1, 0) + IF(ISNUMBER(SEARCH($F$2-3, $F77)), 1, 0) + IF(ISNUMBER(SEARCH($F$2-4, $F77)), 1, 0) + IF(ISNUMBER(SEARCH($F$2-5, $F77)), 1, 0) + IF(ISNUMBER(SEARCH($F$2-6, $F77)), 1, 0) + IF(ISNUMBER(SEARCH($F$2-7, $F77)), 1, 0) + IF(ISNUMBER(SEARCH($F$2-8, $F77)), 1, 0) + IF(ISNUMBER(SEARCH($F$2-9, $F77)), 1, 0) -> 0 | J77: =IF(F77="NA", "NA", IF(G77>0, 1, 0)) -> 0 | K77: =IF(F77="NA","NA",IF(H77>2,1,IF(H77>1,0.5,0))) -> 0 | L77: =IF(F77="NA","NA",IF(I77>5, 1, IF(I77>2, 0.5, 0))) -> 0 | M77: =SUMIF(J77:L77,"<>#N/A") -> 0 | N77: =IF(F77 = "NA", "NA", 0) -> 0 | O77: =IF(F77 = "NA", "NA", 0) -> 0 | P77: =IF(F77 = "NA", "NA", 0) -> 0 | Q77: =IF(F77 = "NA", "NA", 0) -> 0 | R77: =IF(F77 = "NA", "NA", 0) -> 0 | S77: =SUMIF(N77:R77,"<>#N/A") -> 0
A78: CN.EAP.AML.000 | C78: Emissions of Air Pollutants | D78: Annual Mean Levels of Particulate Matter (PM2.5 & PM10) in Cities (1) | G78: =IF(LEN(TRIM(F78)) = 4, 1, IF(LEN(TRIM(F78)) > 5, LEN(TRIM(F78))-LEN(SUBSTITUTE(TRIM(F78),",",""))+1, 0)) -> 0 | H78: =IF(ISNUMBER(SEARCH($F$2, $F78)), 1, 0) + IF(ISNUMBER(SEARCH($F$2-1, $F78)), 1, 0) + IF(ISNUMBER(SEARCH($F$2-2, $F78)), 1, 0) + IF(ISNUMBER(SEARCH($F$2-3, $F78)), 1, 0) + IF(ISNUMBER(SEARCH($F$2-4, $F78)), 1, 0) -> 0 | I78: =IF(ISNUMBER(SEARCH($F$2, $F78)), 1, 0) + IF(ISNUMBER(SEARCH($F$2-1, $F78)), 1, 0) + IF(ISNUMBER(SEARCH($F$2-2, $F78)), 1, 0) + IF(ISNUMBER(SEARCH($F$2-3, $F78)), 1, 0) + IF(ISNUMBER(SEARCH($F$2-4, $F78)), 1, 0) + IF(ISNUMBER(SEARCH($F$2-5, $F78)), 1, 0) + IF(ISNUMBER(SEARCH($F$2-6, $F78)), 1, 0) + IF(ISNUMBER(SEARCH($F$2-7, $F78)), 1, 0) + IF(ISNUMBER(SEARCH($F$2-8, $F78)), 1, 0) + IF(ISNUMBER(SEARCH($F$2-9, $F78)), 1, 0) -> 0 | J78: =IF(F78="NA", "NA", IF(G78>0, 1, 0)) -> 0 | K78: =IF(F78="NA","NA",IF(H78>2,1,IF(H78>1,0.5,0))) -> 0 | L78: =IF(F78="NA","NA",IF(I78>5, 1, IF(I78>2, 0.5, 0))) -> 0 | M78: =SUMIF(J78:L78,"<>#N/A") -> 0 | N78: =IF(F78 = "NA", "NA", 0) -> 0 | O78: =IF(F78 = "NA", "NA", 0) -> 0 | P78: =IF(F78 = "NA", "NA", 0) -> 0 | Q78: =IF(F78 = "NA", "NA", 0) -> 0 | R78: =IF(F78 = "NA", "NA", 0) -> 0 | S78: =SUMIF(N78:R78,"<>#N/A") -> 0
A79: CN.NAD.PDA.000 | C79: Natural Disasters | D79: Persons Directly Affected by Disasters Per 100,000 Population (1) | G79: =IF(LEN(TRIM(F79)) = 4, 1, IF(LEN(TRIM(F79)) > 5, LEN(TRIM(F79))-LEN(SUBSTITUTE(TRIM(F79),",",""))+1, 0)) -> 0 | H79: =IF(ISNUMBER(SEARCH($F$2, $F79)), 1, 0) + IF(ISNUMBER(SEARCH($F$2-1, $F79)), 1, 0) + IF(ISNUMBER(SEARCH($F$2-2, $F79)), 1, 0) + IF(ISNUMBER(SEARCH($F$2-3, $F79)), 1, 0) + IF(ISNUMBER(SEARCH($F$2-4, $F79)), 1, 0) -> 0 | I79: =IF(ISNUMBER(SEARCH($F$2, $F79)), 1, 0) + IF(ISNUMBER(SEARCH($F$2-1, $F79)), 1, 0) + IF(ISNUMBER(SEARCH($F$2-2, $F79)), 1, 0) + IF(ISNUMBER(SEARCH($F$2-3, $F79)), 1, 0) + IF(ISNUMBER(SEARCH($F$2-4, $F79)), 1, 0) + IF(ISNUMBER(SEARCH($F$2-5, $F79)), 1, 0) + IF(ISNUMBER(SEARCH($F$2-6, $F79)), 1, 0) + IF(ISNUMBER(SEARCH($F$2-7, $F79)), 1, 0) + IF(ISNUMBER(SEARCH($F$2-8, $F79)), 1, 0) + IF(ISNUMBER(SEARCH($F$2-9, $F79)), 1, 0) -> 0 | J79: =IF(F79="NA", "NA", IF(G79>0, 1, 0)) -> 0 | K79: =IF(F79="NA","NA",IF(H79>2,1,IF(H79>1,0.5,0))) -> 0 | L79: =IF(F79="NA","NA",IF(I79>5, 1, IF(I79>2, 0.5, 0))) -> 0 | M79: =SUMIF(J79:L79,"<>#N/A") -> 0 | N79: =IF(F79 = "NA", "NA", 0) -> 0 | O79: =IF(F79 = "NA", "NA", 0) -> 0 | P79: =IF(F79 = "NA", "NA", 0) -> 0 | Q79: =IF(F79 = "NA", "NA", 0) -> 0 | R79: =IF(F79 = "NA", "NA", 0) -> 0 | S79: =SUMIF(N79:R79,"<>#N/A") -> 0
A80: CN.RUS.CPA.000 | C80: Resource Use | D80: Coverage of Protected Areas in Relation to Marine Areas (1) | G80: =IF(LEN(TRIM(F80)) = 4, 1, IF(LEN(TRIM(F80)) > 5, LEN(TRIM(F80))-LEN(SUBSTITUTE(TRIM(F80),",",""))+1, 0)) -> 0 | H80: =IF(ISNUMBER(SEARCH($F$2, $F80)), 1, 0) + IF(ISNUMBER(SEARCH($F$2-1, $F80)), 1, 0) + IF(ISNUMBER(SEARCH($F$2-2, $F80)), 1, 0) + IF(ISNUMBER(SEARCH($F$2-3, $F80)), 1, 0) + IF(ISNUMBER(SEARCH($F$2-4, $F80)), 1, 0) -> 0 | I80: =IF(ISNUMBER(SEARCH($F$2, $F80)), 1, 0) + IF(ISNUMBER(SEARCH($F$2-1, $F80)), 1, 0) + IF(ISNUMBER(SEARCH($F$2-2, $F80)), 1, 0) + IF(ISNUMBER(SEARCH($F$2-3, $F80)), 1, 0) + IF(ISNUMBER(SEARCH($F$2-4, $F80)), 1, 0) + IF(ISNUMBER(SEARCH($F$2-5, $F80)), 1, 0) + IF(ISNUMBER(SEARCH($F$2-6, $F80)), 1, 0) + IF(ISNUMBER(SEARCH($F$2-7, $F80)), 1, 0) + IF(ISNUMBER(SEARCH($F$2-8, $F80)), 1, 0) + IF(ISNUMBER(SEARCH($F$2-9, $F80)), 1, 0) -> 0 | J80: =IF(F80="NA", "NA", IF(G80>0, 1, 0)) -> 0 | K80: =IF(F80="NA","NA",IF(H80>2,1,IF(H80>1,0.5,0))) -> 0 | L80: =IF(F80="NA","NA",IF(I80>5, 1, IF(I80>2, 0.5, 0))) -> 0 | M80: =SUMIF(J80:L80,"<>#N/A") -> 0 | N80: =IF(F80 = "NA", "NA", 0) -> 0 | O80: =IF(F80 = "NA", "NA", 0) -> 0 | P80: =IF(F80 = "NA", "NA", 0) -> 0 | Q80: =IF(F80 = "NA", "NA", 0) -> 0 | R80: =IF(F80 = "NA", "NA", 0) -> 0 | S80: =SUMIF(N80:R80,"<>#N/A") -> 0
A81: CN.RUS.FAP.000 | D81: Forest Area as Proportion of Total Land Area (1) | G81: =IF(LEN(TRIM(F81)) = 4, 1, IF(LEN(TRIM(F81)) > 5, LEN(TRIM(F81))-LEN(SUBSTITUTE(TRIM(F81),",",""))+1, 0)) -> 0 | H81: =IF(ISNUMBER(SEARCH($F$2, $F81)), 1, 0) + IF(ISNUMBER(SEARCH($F$2-1, $F81)), 1, 0) + IF(ISNUMBER(SEARCH($F$2-2, $F81)), 1, 0) + IF(ISNUMBER(SEARCH($F$2-3, $F81)), 1, 0) + IF(ISNUMBER(SEARCH($F$2-4, $F81)), 1, 0) -> 0 | I81: =IF(ISNUMBER(SEARCH($F$2, $F81)), 1, 0) + IF(ISNUMBER(SEARCH($F$2-1, $F81)), 1, 0) + IF(ISNUMBER(SEARCH($F$2-2, $F81)), 1, 0) + IF(ISNUMBER(SEARCH($F$2-3, $F81)), 1, 0) + IF(ISNUMBER(SEARCH($F$2-4, $F81)), 1, 0) + IF(ISNUMBER(SEARCH($F$2-5, $F81)), 1, 0) + IF(ISNUMBER(SEARCH($F$2-6, $F81)), 1, 0) + IF(ISNUMBER(SEARCH($F$2-7, $F81)), 1, 0) + IF(ISNUMBER(SEARCH($F$2-8, $F81)), 1, 0) + IF(ISNUMBER(SEARCH($F$2-9, $F81)), 1, 0) -> 0 | J81: =IF(F81="NA", "NA", IF(G81>0, 1, 0)) -> 0 | K81: =IF(F81="NA","NA",IF(H81>2,1,IF(H81>1,0.5,0))) -> 0 | L81: =IF(F81="NA","NA",IF(I81>5, 1, IF(I81>2, 0.5, 0))) -> 0 | M81: =SUMIF(J81:L81,"<>#N/A") -> 0 | N81: =IF(F81 = "NA", "NA", 0) -> 0 | O81: =IF(F81 = "NA", "NA", 0) -> 0 | P81: =IF(F81 = "NA", "NA", 0) -> 0 | Q81: =IF(F81 = "NA", "NA", 0) -> 0 | R81: =IF(F81 = "NA", "NA", 0) -> 0 | S81: =SUMIF(N81:R81,"<>#N/A") -> 0
B82: Total | J82: =SUM(J5:J81) -> 0 | K82: =SUM(K5:K81) -> 0 | L82: =SUM(L5:L81) -> 0 | M82: =SUM(M5:M81) -> 0 | N82: =SUMIF(N5:N81,"<>#N/A") -> 0 | O82: =SUMIF(O5:O81,"<>#N/A") -> 0 | P82: =SUMIF(P5:P81,"<>#N/A") -> 0 | Q82: =SUMIF(Q5:Q81,"<>#N/A") -> 0 | R82: =SUMIF(R5:R81,"<>#N/A") -> 0 | S82: =SUMIF(S5:S81,"<>#N/A") -> 0
B85: Note:
B86: 1. Please fill in the yellow cell only, the gray cell is auto fill by formula and the blue cell is for ASEANstats only
B87: 2. Click on the header title for the explanation
B88: 3. No need to fill the summary report, the summary report is auto calculated based on this worksheed (Input)
B92: Section | D92: Counts of NA
B93: Social-Demography | D93: =COUNTIF(F5:F36, "NA") -> 0
B94: Macroeconomic | D94: =COUNTIF(F37:F50, "NA") -> 0
B95: Trade & Investment | D95: =COUNTIF(F51:F65, "NA") -> 4
B96: Connectivity & Environment | D96: =COUNTIF(F66:F81,"NA") -> 1

Sheet Summary Report
B1: ACSS Open Data Score
B3: ASEAN Member States
B4: Sections | C4: Coverage | F4: Opennes | I4: Overall Score
C5: Max Score | D5: Actual Score | E5: Sub Score | F5: Max Score | G5: Actual Score | H5: Sub Score
B6: (A) Social-Demography | C6: =(32-Input!D93)*3 -> 96 | D6: =SUM(Input!M$5:M$36) -> 0 | E6: =(D6/C6)*100% -> 0 | F6: =(32-Input!D93)*5 -> 160 | G6: =SUM(Input!S$5:S$36) -> 0 | H6: =(G6/F6)*100% -> 0 | I6: =(D6/C6)*50%+(G6/F6)*50% -> 0
B7: (B) Macroeconomic | C7: =(14-Input!D94)*3 -> 42 | D7: =SUM(Input!M$37:M$50) -> 0 | E7: =(D7/C7)*100% -> 0 | F7: =(14-Input!D94)*5 -> 70 | G7: =SUM(Input!S$37:S$50) -> 0 | H7: =(G7/F7)*100% -> 0 | I7: =(D7/C7)*50%+(G7/F7)*50% -> 0
B8: (C) Trade & Investment | C8: =(15-Input!D95)*3 -> 33 | D8: =SUM(Input!M$51:M$65)-Input!M55-Input!M61-Input!M65 -> 0 | E8: =(D8/C8)*100% -> 0 | F8: =(15-Input!D95)*5 -> 55 | G8: =SUM(Input!S$51:S$65)-Input!S55-Input!S61-Input!S65 -> 0 | H8: =(G8/F8)*100% -> 0 | I8: =(D8/C8)*50%+(G8/F8)*50% -> 0
B9: (D) Connectivity & Environment | C9: =(16-Input!D96)*3 -> 45 | D9: =SUM(Input!M$66:M$81)-Input!M68 -> 0 | E9: =(D9/C9)*100% -> 0 | F9: =(16-Input!D96)*5 -> 75 | G9: =SUM(Input!S$66:S$81)-Input!S68 -> 0 | H9: =(G9/F9)*100% -> 0 | I9: =(D9/C9)*50%+(G9/F9)*50% -> 0
B10: Weighted Score | C10: Coverage weighted sub score: | E10: =(D6/C6)*25%+(D7/C7)*25%+ (D8/C8)*25% + (D9/C9)*25% -> 0 | F10: Opennes weighted sub score: | H10: =(G6/F6)*25%+(G7/F7)*25%+ (G8/F8)*25% + (G9/F9)*25% -> 0 | I10: =(E10*50%)+(H10*50%) -> 0
B13: Max coverage score = number of indicator and disaggregation * 3
B14: Max openness score = number of indicator and disaggregation * 5

Sheet Scoring Guideline
B2: Coverage Scoring Guidelines
B4: C1 - Disaggregation
B5: Point | D5: Condition | E5: Notes
B6: 1 | C6: Point | D6: if the published data and its required disaggregation/ breakdown are available. | E6: Indicator(s) that are not applicable to the AMS will be excluded from country assessment for all elements of coverage and openness. E.g., i.Indicators with the disaggregation ‘Intra and Extra’ is applicable to ASEANStats only. AMSs will not be assessed for these indicators for all elements of Coverage and Openness. ii.‘Proportion of Population Living below National Poverty Line’ is not applicable to Brunei Darussalam and Singapore and will not be assessed for these indicators for all elements of Coverage and Openness.
B7: 0 | C7: Point | D7: if the published data and its required disaggregation/ breakdown are NOT available.
B8: Indicator(s) that scored 0 for C1 will be awarded 0 point for all data elements of coverage and openness (i.e., C1-C3 and O1-O5)
B10: C2 – Availability of Data for Last 5 Years
B11: Point | D11: Condition | E11: Notes
B12: 1 | C12: Point | D12: if the published data and its required disaggregation/ breakdown are available for at least 3 of the last 5 years. | E12: E.g., the 3 years must occur within 2013-2017 (or 2012/2013-2016/2017). If the indicator shows data for a non-calendar year (i.e. 2012/2013), this should be counted as one year. Overlapping years (such as 2013 and 2013/14 for a single indicator) should not be double counted.
B13: 0.5 | C13: Point | D13: if the published data and its required disaggregation/ breakdown are available for 1 or 2 of the last 5 years. | E13: E.g., the 1-2 years must occur within 2013-2017 (or 2012/2013-2016/2017). If the indicator shows data for a non-calendar year (i.e. 2013/2014), this should be counted as one year.
B14: 0 | C14: Point | D14: if the published data and its required disaggregation/ breakdown are NOT available.
B16: C3 – Availability of Data for Last 10 Years
B17: Point | D17: Condition | E17: Notes
B18: 1 | C18: Point | D18: if the published data and its required disaggregation/ breakdown are available for at least 6 of the last 10 years. | E18: E.g., the 6 years must occur within 2008-2017 (or 2007/2008-2016/2017). If the indicator shows data for a non-calendar year (i.e. 2013/2014), this should be counted as one year. Overlapping years (2013 and 2013/14) should not be double counted.
B19: 0.5 | C19: Point | D19: if the published data and its required disaggregation/ breakdown are available for 3 to 5 of the last 10 years. | E19: E.g., the 3-5 years must occur within 2007-2016 (or 2007/2008-2016/2017). If the indicator shows data for a non-calendar year (i.e. 2013/2014), this should be counted as one year. Overlapping years (2013 and 2013/14) should not be double counted.
B20: 0 | C20: Point | D20: if the published data and its required disaggregation/ breakdown are available for 2 or fewer of the last 10 years.
B24: Openness Scoring Guidelines
B26: O1 – Machine Readability
B27: Point | D27: Condition | E27: Notes
B28: 1 | C28: Point | D28: if the published data and its required disaggregation/ breakdown are available in machine readable format (such as XLSX, CSV, TXT, JSON and XML). | E28: PDF document containing tables of data are not machine-readable because a computer would struggle to access the tabular information. The equivalent tables in a format such as a spreadsheet would be machine readable. As another example scans (photographs) of text are not machine-readable but the equivalent text in a format such as a simple ASCII text file can machine readable and processable. If published data are available in both machine readable and non-machine readable formats, a full point should be awarded for machine readability
B29: 0 | C29: Point | D29: if all published data and its required disaggregation/ breakdown are not available in machine-readable format.
B32: O2 – Non-Proprietary
B33: Point | D33: Condition | E33: Notes
B34: 1 | C34: Point | D34: if the published data and its required disaggregation/ breakdown are available in non-proprietary format (such as XLSX, CSV, XML, TXT and JSON). | E34: XLS, Stata, SAS, SPSS, DOC and PPT files are proprietary. If published data are available in both proprietary and non-proprietary formats, a full point would be awarded.
B35: 0 | C35: Point | D35: if the published data and its required disaggregation/ breakdown are not available in non-proprietary format | E35: A zero point is only given if no data in a data category is available in this format or if all data files are compressed in RAR format. ZIP compression is non-proprietary and does not affect score.
B38: O3 – Download Options
B39: Point | D39: Condition | E39: Notes
B40: 1 | C40: Point | D40: if the website containing the published data and its required disaggregation/ breakdown has a bulk download option AND an API or user-selectable download option. | E40: Assessment is based on the ability to bulk download on the NSO’s website or line ministries’ website (linked from NSO’s website).
B41: 0.5 | C41: Point | D41: if the website containing the published data and its required disaggregation/ breakdown has an API, bulk download, or user-selectable download options. | E41: Assessment is based on the ability to bulk download on the NSO’s website or line ministries’ website (linked from NSO’s website).
B42: 0 | C42: Point | D42: if the website containing the published data and its required disaggregation/ breakdown does not have any API, bulk download, or user-selectable download options. | E42: Assessment is based on the ability to bulk download on the NSO’s website or line ministries’ website (linked from NSO’s website).
B45: O4 – Metadata Availability
B46: Point | D46: Condition | E46: Notes
B47: 1 | C47: Point | D47: if the published data and its required disaggregation/ breakdown has all metadata fields. | E47: Full point if metadata contains all of the following fields in line with the Concept Note on ACSS Open Data Initiative on Statistics adopted at ACSS8. a.definition; b.frequency; c.unit of measure; d.level of disaggregation; e.data source; f.availability (start & end periods); g.URL for direct access to data series/ statistical table; h.formats for download; and i.URL to terms of use Metadata may be included in the same file as data or it can be included elsewhere on the NSO website (this may happen if data are in a regularly published report, survey, or census).
B48: 0.5 | C48: Point | D48: if the published data and its required disaggregation/ breakdown has at least 5 of the metadata fields. | E48: Half a point if metadata contains at least 5 of the fields a to i as listed above.
B49: 0 | C49: Point | D49: if the published data and its required disaggregation/ breakdown has 4 or less of the metadata fields.
B52: O5 – Term of Use
B53: Point | D53: Condition | E53: Notes
B54: 1 | C54: Point | D54: if the website containing the published data and its required disaggregation/ breakdown has a terms of use classified as open. | E54: AMSs may refer to the ODIN’s Terms of Use score for their respective website. Full point if their website TOUs is considered “Fully Open”.
B55: 0.5 | C55: Point | D55: if the website containing the published data and its required disaggregation/ breakdown has a terms of use classified as semi-restrictive. | E55: AMSs may refer to the ODIN’s Terms of Use score for their respective website. Half a point if their website TOUs is considered “Semi-restrictive”.
B56: 0 | C56: Point | D56: if the website containing the published data and its required disaggregation/ breakdown has a terms of use classified as restrictive or does not have any terms of use. | E56: AMSs may refer to the ODIN’s Terms of Use score for their respective website. Zero point if their website TOUs is considered “Restrictive”.

Sheet Sheet1
A1: Not Available | B1: Not applicable | C1: Machine Readability | D1: Non-Proprietary | E1: Download Options | F1: Metadata Availability | G1: Terms of Use
A2: 0 | B2: NA | C2: 0 | D2: 0 | E2: 0 | F2: 0 | G2: 0
C3: 1 | D3: 1 | E3: 0.5 | F3: 0.5 | G3: 0.5
E4: 1 | F4: 1 | G4: 1
